[{
  "transactionId": null,
  "pairTransactionId": null,
  "accountId": "d79ec11a-2011-4423-ba01-3af8de0a3e14",
  "date": "2018-10-17T06:00+10:00",
  "stockSymbol": "MAT",
  "stockPrice": 14.83,
  "strikePrice": 14.0,
  "expiryDate": "2018-11-16T00:00+10:00",
  "impliedVolatility": null,
  "historicalImpliedVolatility": null,
  "profitProbability": null,
  "contracts": 3,
  "premium": 0.55,
  "action": "SELL",
  "actionType": "PUT",
  "brokerFees": 0.0,
  "mark": 1
}
,
{
"transactionId": null,
"pairTransactionId": null,
"accountId": "d79ec11a-2011-4423-ba01-3af8de0a3e14",
"date": "2018-11-03T06:00+10:00",
"stockSymbol": "MAT",
"stockPrice": 0.0,
"strikePrice": 14.0,
"expiryDate": "2018-11-16T00:00+10:00",
"impliedVolatility": null,
"historicalImpliedVolatility": null,
"profitProbability": null,
"contracts": 3,
"premium": -0.30,
"action": "BUY",
"actionType": "PUT",
"brokerFees": 0.0,
"mark": 1
},

{
"transactionId": null,
"pairTransactionId": null,
"accountId": "d79ec11a-2011-4423-ba01-3af8de0a3e14",
"date": "2018-10-31T06:00+10:00",
"stockSymbol": "PGR",
"stockPrice": 60.87,
"strikePrice": 70.0,
"expiryDate": "2018-11-16T00:00+10:00",
"impliedVolatility": null,
"historicalImpliedVolatility": null,
"profitProbability": null,
"contracts": 1,
"premium": 2.50,
"action": "SELL",
"actionType": "PUT",
"brokerFees": 0.0,
"mark": 1
}
,
{
"transactionId": null,
"pairTransactionId": null,
"accountId": "d79ec11a-2011-4423-ba01-3af8de0a3e14",
"date": "2018-11-13T06:00+10:00",
"stockSymbol": "PGR",
"stockPrice": 0.0,
"strikePrice": 70.0,
"expiryDate": "2018-11-16T00:00+10:00",
"impliedVolatility": null,
"historicalImpliedVolatility": null,
"profitProbability": null,
"contracts": 1,
"premium": -0.38,
"action": "BUY",
"actionType": "PUT",
"brokerFees": 0.0,
"mark": 1
},

{
"transactionId": null,
"pairTransactionId": null,
"accountId": "d79ec11a-2011-4423-ba01-3af8de0a3e14",
"date": "2018-10-31T06:00+10:00",
"stockSymbol": "HIIQ",
"stockPrice": 48.96,
"strikePrice": 45.0,
"expiryDate": "2018-11-16T00:00+10:00",
"impliedVolatility": null,
"historicalImpliedVolatility": null,
"profitProbability": null,
"contracts": 1,
"premium": 1.85,
"action": "SELL",
"actionType": "PUT",
"brokerFees": 0.0,
"mark": 1
}
,
{
"transactionId": null,
"pairTransactionId": null,
"accountId": "d79ec11a-2011-4423-ba01-3af8de0a3e14",
"date": "2018-11-17T06:00+10:00",
"stockSymbol": "HIIQ",
"stockPrice": 0.0,
"strikePrice": 45.0,
"expiryDate": "2018-11-16T00:00+10:00",
"impliedVolatility": null,
"historicalImpliedVolatility": null,
"profitProbability": null,
"contracts": 1,
"premium": 0.00,
"action": "BUY",
"actionType": "PUT",
"brokerFees": 0.31,
"mark": 1
},

{
"transactionId": null,
"pairTransactionId": null,
"accountId": "d79ec11a-2011-4423-ba01-3af8de0a3e14",
"date": "2018-11-08T06:00+10:00",
"stockSymbol": "TWTR",
"stockPrice": 34.79,
"strikePrice": 35.0,
"expiryDate": "2018-12-21T00:00+10:00",
"impliedVolatility": null,
"historicalImpliedVolatility": null,
"profitProbability": null,
"contracts": 2,
"premium": 2.11,
"action": "SELL",
"actionType": "PUT",
"brokerFees": 0.0,
"mark": 1
}
,
{
"transactionId": null,
"pairTransactionId": null,
"accountId": "d79ec11a-2011-4423-ba01-3af8de0a3e14",
"date": "2018-12-12T06:00+10:00",
"stockSymbol": "TWTR",
"stockPrice": 0.0,
"strikePrice": 35.0,
"expiryDate": "2018-12-21T00:00+10:00",
"impliedVolatility": null,
"historicalImpliedVolatility": null,
"profitProbability": null,
"contracts": 2,
"premium": -0.70,
"action": "BUY",
"actionType": "PUT",
"brokerFees": 0.0,
"mark": 1
},

{
"transactionId": null,
"pairTransactionId": null,
"accountId": "d79ec11a-2011-4423-ba01-3af8de0a3e14",
"date": "2018-11-08T06:00+10:00",
"stockSymbol": "CYBR",
"stockPrice": 70.63,
"strikePrice": 70.0,
"expiryDate": "2018-12-21T00:00+10:00",
"impliedVolatility": null,
"historicalImpliedVolatility": null,
"profitProbability": null,
"contracts": 1,
"premium": 4.35,
"action": "SELL",
"actionType": "PUT",
"brokerFees": 0.0,
"mark": 1
}
,
{
"transactionId": null,
"pairTransactionId": null,
"accountId": "d79ec11a-2011-4423-ba01-3af8de0a3e14",
"date": "2018-11-13T06:00+10:00",
"stockSymbol": "CYBR",
"stockPrice": 0.0,
"strikePrice": 70.0,
"expiryDate": "2018-12-21T00:00+10:00",
"impliedVolatility": null,
"historicalImpliedVolatility": null,
"profitProbability": null,
"contracts": 1,
"premium": -1.53,
"action": "BUY",
"actionType": "PUT",
"brokerFees": 0.0,
"mark": 1
},

{
"transactionId": null,
"pairTransactionId": null,
"accountId": "d79ec11a-2011-4423-ba01-3af8de0a3e14",
"date": "2018-11-14T06:00+10:00",
"stockSymbol": "CIEN",
"stockPrice": 33.31,
"strikePrice": 32.0,
"expiryDate": "2018-12-21T00:00+10:00",
"impliedVolatility": null,
"historicalImpliedVolatility": null,
"profitProbability": null,
"contracts": 2,
"premium": 1.40,
"action": "SELL",
"actionType": "PUT",
"brokerFees": 0.0,
"mark": 1
}
,
{
"transactionId": null,
"pairTransactionId": null,
"accountId": "d79ec11a-2011-4423-ba01-3af8de0a3e14",
"date": "2018-12-13T06:00+10:00",
"stockSymbol": "CIEN",
"stockPrice": 0.0,
"strikePrice": 32.0,
"expiryDate": "2018-12-21T00:00+10:00",
"impliedVolatility": null,
"historicalImpliedVolatility": null,
"profitProbability": null,
"contracts": 2,
"premium": -0.20,
"action": "BUY",
"actionType": "PUT",
"brokerFees": 0.0,
"mark": 1
},

{
"transactionId": null,
"pairTransactionId": null,
"accountId": "d79ec11a-2011-4423-ba01-3af8de0a3e14",
"date": "2018-11-15T06:00+10:00",
"stockSymbol": "BEAT",
"stockPrice": 60.94,
"strikePrice": 60.0,
"expiryDate": "2018-12-21T00:00+10:00",
"impliedVolatility": null,
"historicalImpliedVolatility": null,
"profitProbability": null,
"contracts": 1,
"premium": 3.00,
"action": "SELL",
"actionType": "PUT",
"brokerFees": 0.0,
"mark": 1
}
,
{
"transactionId": null,
"pairTransactionId": null,
"accountId": "d79ec11a-2011-4423-ba01-3af8de0a3e14",
"date": "2018-11-28T06:00+10:00",
"stockSymbol": "BEAT",
"stockPrice": 0.0,
"strikePrice": 60.0,
"expiryDate": "2018-12-21T00:00+10:00",
"impliedVolatility": null,
"historicalImpliedVolatility": null,
"profitProbability": null,
"contracts": 1,
"premium": -0.60,
"action": "BUY",
"actionType": "PUT",
"brokerFees": 0.0,
"mark": 1
},

{
"transactionId": null,
"pairTransactionId": null,
"accountId": "d79ec11a-2011-4423-ba01-3af8de0a3e14",
"date": "2018-11-20T06:00+10:00",
"stockSymbol": "NOMD",
"stockPrice": 19.55,
"strikePrice": 20.0,
"expiryDate": "2018-12-21T00:00+10:00",
"impliedVolatility": null,
"historicalImpliedVolatility": null,
"profitProbability": null,
"contracts": 3,
"premium": 0.80,
"action": "SELL",
"actionType": "PUT",
"brokerFees": 0.0,
"mark": 1
}
,
{
"transactionId": null,
"pairTransactionId": null,
"accountId": "d79ec11a-2011-4423-ba01-3af8de0a3e14",
"date": "2018-12-21T06:00+10:00",
"stockSymbol": "NOMD",
"stockPrice": 0.0,
"strikePrice": 20.0,
"expiryDate": "2018-12-21T00:00+10:00",
"impliedVolatility": null,
"historicalImpliedVolatility": null,
"profitProbability": null,
"contracts": 3,
"premium": 0.00,
"action": "BUY",
"actionType": "PUT",
"brokerFees": 0.0,
"mark": 1
},

{
"transactionId": null,
"pairTransactionId": null,
"accountId": "d79ec11a-2011-4423-ba01-3af8de0a3e14",
"date": "2018-11-23T06:00+10:00",
"stockSymbol": "ABT",
"stockPrice": 68.53,
"strikePrice": 66.0,
"expiryDate": "2018-12-21T00:00+10:00",
"impliedVolatility": null,
"historicalImpliedVolatility": null,
"profitProbability": null,
"contracts": 1,
"premium": 0.92,
"action": "SELL",
"actionType": "PUT",
"brokerFees": 0.0,
"mark": 1
}
,
{
"transactionId": null,
"pairTransactionId": null,
"accountId": "d79ec11a-2011-4423-ba01-3af8de0a3e14",
"date": "2018-11-28T06:00+10:00",
"stockSymbol": "ABT",
"stockPrice": 0.0,
"strikePrice": 66.0,
"expiryDate": "2018-12-21T00:00+10:00",
"impliedVolatility": null,
"historicalImpliedVolatility": null,
"profitProbability": null,
"contracts": 1,
"premium": -0.22,
"action": "BUY",
"actionType": "PUT",
"brokerFees": 0.0,
"mark": 1
},

{
"transactionId": null,
"pairTransactionId": null,
"accountId": "d79ec11a-2011-4423-ba01-3af8de0a3e14",
"date": "2018-11-29T06:00+10:00",
"stockSymbol": "FOXF",
"stockPrice": 64.68,
"strikePrice": 60.0,
"expiryDate": "2018-12-21T00:00+10:00",
"impliedVolatility": null,
"historicalImpliedVolatility": null,
"profitProbability": null,
"contracts": 1,
"premium": 1.45,
"action": "SELL",
"actionType": "PUT",
"brokerFees": 0.0,
"mark": 1
}
,
{
"transactionId": null,
"pairTransactionId": null,
"accountId": "d79ec11a-2011-4423-ba01-3af8de0a3e14",
"date": "2018-12-11T06:00+10:00",
"stockSymbol": "FOXF",
"stockPrice": 0.0,
"strikePrice": 60.0,
"expiryDate": "2018-12-21T00:00+10:00",
"impliedVolatility": null,
"historicalImpliedVolatility": null,
"profitProbability": null,
"contracts": 1,
"premium": -0.65,
"action": "BUY",
"actionType": "PUT",
"brokerFees": 0.0,
"mark": 1
},

{
"transactionId": null,
"pairTransactionId": null,
"accountId": "d79ec11a-2011-4423-ba01-3af8de0a3e14",
"date": "2018-12-04T06:00+10:00",
"stockSymbol": "HIIQ",
"stockPrice": 32.86,
"strikePrice": 43.0,
"expiryDate": "2018-12-21T00:00+10:00",
"impliedVolatility": null,
"historicalImpliedVolatility": null,
"profitProbability": null,
"contracts": 1,
"premium": 0.35,
"action": "SELL",
"actionType": "CALL",
"brokerFees": 0.0,
"mark": 1
}
,
{
"transactionId": null,
"pairTransactionId": null,
"accountId": "d79ec11a-2011-4423-ba01-3af8de0a3e14",
"date": "2018-12-17T06:00+10:00",
"stockSymbol": "HIIQ",
"stockPrice": 0.0,
"strikePrice": 43.0,
"expiryDate": "2018-12-21T00:00+10:00",
"impliedVolatility": null,
"historicalImpliedVolatility": null,
"profitProbability": null,
"contracts": 1,
"premium": -0.10,
"action": "BUY",
"actionType": "CALL",
"brokerFees": 0.0,
"mark": 1
},

{
"transactionId": null,
"pairTransactionId": null,
"accountId": "d79ec11a-2011-4423-ba01-3af8de0a3e14",
"date": "2018-12-12T06:00+10:00",
"stockSymbol": "SMPL",
"stockPrice": 19.40,
"strikePrice": 20.0,
"expiryDate": "2018-01-18T00:00+10:00",
"impliedVolatility": null,
"historicalImpliedVolatility": null,
"profitProbability": null,
"contracts": 2,
"premium": 0.85,
"action": "SELL",
"actionType": "PUT",
"brokerFees": 0.0,
"mark": 1
}
,
{
"transactionId": null,
"pairTransactionId": null,
"accountId": "d79ec11a-2011-4423-ba01-3af8de0a3e14",
"date": "2019-01-17T06:00+10:00",
"stockSymbol": "SMPL",
"stockPrice": 0.0,
"strikePrice": 20.0,
"expiryDate": "2018-01-18T00:00+10:00",
"impliedVolatility": null,
"historicalImpliedVolatility": null,
"profitProbability": null,
"contracts": 2,
"premium": -0.20,
"action": "BUY",
"actionType": "PUT",
"brokerFees": 0.0,
"mark": 1
},

{
"transactionId": null,
"pairTransactionId": null,
"accountId": "d79ec11a-2011-4423-ba01-3af8de0a3e14",
"date": "2018-12-13T06:00+10:00",
"stockSymbol": "PLNT",
"stockPrice": 54.38,
"strikePrice": 52.5,
"expiryDate": "2018-01-18T00:00+10:00",
"impliedVolatility": null,
"historicalImpliedVolatility": null,
"profitProbability": null,
"contracts": 1,
"premium": 1.55,
"action": "SELL",
"actionType": "PUT",
"brokerFees": 0.0,
"mark": 1
}
,
{
"transactionId": null,
"pairTransactionId": null,
"accountId": "d79ec11a-2011-4423-ba01-3af8de0a3e14",
"date": "2019-01-09T06:00+10:00",
"stockSymbol": "PLNT",
"stockPrice": 0.0,
"strikePrice": 52.5,
"expiryDate": "2018-01-18T00:00+10:00",
"impliedVolatility": null,
"historicalImpliedVolatility": null,
"profitProbability": null,
"contracts": 1,
"premium": -0.22,
"action": "BUY",
"actionType": "PUT",
"brokerFees": 0.0,
"mark": 1
},

{
"transactionId": null,
"pairTransactionId": null,
"accountId": "d79ec11a-2011-4423-ba01-3af8de0a3e14",
"date": "2018-12-14T06:00+10:00",
"stockSymbol": "CIEN",
"stockPrice": 34.32,
"strikePrice": 34.0,
"expiryDate": "2018-04-18T00:00+10:00",
"impliedVolatility": null,
"historicalImpliedVolatility": null,
"profitProbability": null,
"contracts": 2,
"premium": 2.49,
"action": "SELL",
"actionType": "PUT",
"brokerFees": 0.0,
"mark": 1
}
,
{
"transactionId": null,
"pairTransactionId": null,
"accountId": "d79ec11a-2011-4423-ba01-3af8de0a3e14",
"date": "2019-01-10T06:00+10:00",
"stockSymbol": "CIEN",
"stockPrice": 0.0,
"strikePrice": 34.0,
"expiryDate": "2018-04-18T00:00+10:00",
"impliedVolatility": null,
"historicalImpliedVolatility": null,
"profitProbability": null,
"contracts": 2,
"premium": -1.57,
"action": "BUY",
"actionType": "PUT",
"brokerFees": 0.0,
"mark": 1
},

{
"transactionId": null,
"pairTransactionId": null,
"accountId": "d79ec11a-2011-4423-ba01-3af8de0a3e14",
"date": "2018-12-17T06:00+10:00",
"stockSymbol": "TWTR",
"stockPrice": 33.54,
"strikePrice": 31.0,
"expiryDate": "2018-03-15T00:00+10:00",
"impliedVolatility": null,
"historicalImpliedVolatility": null,
"profitProbability": null,
"contracts": 2,
"premium": 2.51,
"action": "SELL",
"actionType": "PUT",
"brokerFees": 0.0,
"mark": 1
}
,
{
"transactionId": null,
"pairTransactionId": null,
"accountId": "d79ec11a-2011-4423-ba01-3af8de0a3e14",
"date": "2019-01-25T06:00+10:00",
"stockSymbol": "TWTR",
"stockPrice": 0.0,
"strikePrice": 31.0,
"expiryDate": "2018-03-15T00:00+10:00",
"impliedVolatility": null,
"historicalImpliedVolatility": null,
"profitProbability": null,
"contracts": 2,
"premium": -1.90,
"action": "BUY",
"actionType": "PUT",
"brokerFees": 0.0,
"mark": 1
},

{
"transactionId": null,
"pairTransactionId": null,
"accountId": "d79ec11a-2011-4423-ba01-3af8de0a3e14",
"date": "2018-12-17T06:00+10:00",
"stockSymbol": "HIIQ",
"stockPrice": 30.37,
"strikePrice": 42.0,
"expiryDate": "2018-02-15T00:00+10:00",
"impliedVolatility": null,
"historicalImpliedVolatility": null,
"profitProbability": null,
"contracts": 1,
"premium": 1.17,
"action": "SELL",
"actionType": "CALL",
"brokerFees": 0.0,
"mark": 1
}
,
{
"transactionId": null,
"pairTransactionId": null,
"accountId": "d79ec11a-2011-4423-ba01-3af8de0a3e14",
"date": "2019-02-12T06:00+10:00",
"stockSymbol": "HIIQ",
"stockPrice": 0.0,
"strikePrice": 42.0,
"expiryDate": "2018-02-15T00:00+10:00",
"impliedVolatility": null,
"historicalImpliedVolatility": null,
"profitProbability": null,
"contracts": 1,
"premium": -0.50,
"action": "BUY",
"actionType": "CALL",
"brokerFees": 0.0,
"mark": 1
},

{
"transactionId": null,
"pairTransactionId": null,
"accountId": "d79ec11a-2011-4423-ba01-3af8de0a3e14",
"date": "2018-12-19T06:00+10:00",
"stockSymbol": "TOL",
"stockPrice": 33.09,
"strikePrice": 32.0,
"expiryDate": "2018-03-15T00:00+10:00",
"impliedVolatility": null,
"historicalImpliedVolatility": null,
"profitProbability": null,
"contracts": 1,
"premium": 1.80,
"action": "SELL",
"actionType": "PUT",
"brokerFees": 0.0,
"mark": 1
}
,
{
"transactionId": null,
"pairTransactionId": null,
"accountId": "d79ec11a-2011-4423-ba01-3af8de0a3e14",
"date": "2019-01-10T06:00+10:00",
"stockSymbol": "TOL",
"stockPrice": 0.0,
"strikePrice": 32.0,
"expiryDate": "2018-03-15T00:00+10:00",
"impliedVolatility": null,
"historicalImpliedVolatility": null,
"profitProbability": null,
"contracts": 1,
"premium": -0.80,
"action": "BUY",
"actionType": "PUT",
"brokerFees": 0.0,
"mark": 1
},

{
"transactionId": null,
"pairTransactionId": null,
"accountId": "d79ec11a-2011-4423-ba01-3af8de0a3e14",
"date": "2019-01-10T06:00+10:00",
"stockSymbol": "CIEN",
"stockPrice": 36.89,
"strikePrice": 37.0,
"expiryDate": "2019-01-18T00:00+10:00",
"impliedVolatility": null,
"historicalImpliedVolatility": null,
"profitProbability": null,
"contracts": 1,
"premium": -0.85,
"action": "BUY",
"actionType": "PUT",
"brokerFees": 0.0,
"mark": 1
}
,
{
"transactionId": null,
"pairTransactionId": null,
"accountId": "d79ec11a-2011-4423-ba01-3af8de0a3e14",
"date": "2019-01-18T06:00+10:00",
"stockSymbol": "CIEN",
"stockPrice": 0.0,
"strikePrice": 37.0,
"expiryDate": "2019-01-18T00:00+10:00",
"impliedVolatility": null,
"historicalImpliedVolatility": null,
"profitProbability": null,
"contracts": 1,
"premium": 0.00,
"action": "SELL",
"actionType": "PUT",
"brokerFees": 0.0,
"mark": 1
},

{
"transactionId": null,
"pairTransactionId": null,
"accountId": "d79ec11a-2011-4423-ba01-3af8de0a3e14",
"date": "2019-01-17T06:00+10:00",
"stockSymbol": "NOMD",
"stockPrice": 17.86,
"strikePrice": 17.5,
"expiryDate": "2019-02-15T00:00+10:00",
"impliedVolatility": null,
"historicalImpliedVolatility": null,
"profitProbability": null,
"contracts": 3,
"premium": 0.40,
"action": "SELL",
"actionType": "PUT",
"brokerFees": 0.0,
"mark": 1
}
,
{
"transactionId": null,
"pairTransactionId": null,
"accountId": "d79ec11a-2011-4423-ba01-3af8de0a3e14",
"date": "2019-01-30T06:00+10:00",
"stockSymbol": "NOMD",
"stockPrice": 0.0,
"strikePrice": 17.5,
"expiryDate": "2019-02-15T00:00+10:00",
"impliedVolatility": null,
"historicalImpliedVolatility": null,
"profitProbability": null,
"contracts": 3,
"premium": -0.20,
"action": "BUY",
"actionType": "PUT",
"brokerFees": 0.0,
"mark": 1
},

{
"transactionId": null,
"pairTransactionId": null,
"accountId": "d79ec11a-2011-4423-ba01-3af8de0a3e14",
"date": "2019-01-22T06:00+10:00",
"stockSymbol": "AMAT",
"stockPrice": 34.47,
"strikePrice": 33.0,
"expiryDate": "2019-02-15T00:00+10:00",
"impliedVolatility": null,
"historicalImpliedVolatility": null,
"profitProbability": null,
"contracts": 1,
"premium": 0.91,
"action": "SELL",
"actionType": "PUT",
"brokerFees": 0.0,
"mark": 1
}
,
{
"transactionId": null,
"pairTransactionId": null,
"accountId": "d79ec11a-2011-4423-ba01-3af8de0a3e14",
"date": "2019-01-23T06:00+10:00",
"stockSymbol": "AMAT",
"stockPrice": 0.0,
"strikePrice": 33.0,
"expiryDate": "2019-02-15T00:00+10:00",
"impliedVolatility": null,
"historicalImpliedVolatility": null,
"profitProbability": null,
"contracts": 1,
"premium": -0.38,
"action": "BUY",
"actionType": "PUT",
"brokerFees": 0.0,
"mark": 1
},

{
"transactionId": null,
"pairTransactionId": null,
"accountId": "d79ec11a-2011-4423-ba01-3af8de0a3e14",
"date": "2019-01-23T06:00+10:00",
"stockSymbol": "EXEL",
"stockPrice": 22.71,
"strikePrice": 22.0,
"expiryDate": "2019-02-15T00:00+10:00",
"impliedVolatility": null,
"historicalImpliedVolatility": null,
"profitProbability": null,
"contracts": 1,
"premium": 1.05,
"action": "SELL",
"actionType": "PUT",
"brokerFees": 0.0,
"mark": 1
}
,
{
"transactionId": null,
"pairTransactionId": null,
"accountId": "d79ec11a-2011-4423-ba01-3af8de0a3e14",
"date": "2019-02-01T06:00+10:00",
"stockSymbol": "EXEL",
"stockPrice": 0.0,
"strikePrice": 22.0,
"expiryDate": "2019-02-15T00:00+10:00",
"impliedVolatility": null,
"historicalImpliedVolatility": null,
"profitProbability": null,
"contracts": 1,
"premium": -0.80,
"action": "BUY",
"actionType": "PUT",
"brokerFees": 0.0,
"mark": 1
},

{
"transactionId": null,
"pairTransactionId": null,
"accountId": "d79ec11a-2011-4423-ba01-3af8de0a3e14",
"date": "2019-01-24T06:00+10:00",
"stockSymbol": "CVS",
"stockPrice": 65.75,
"strikePrice": 64.0,
"expiryDate": "2019-02-15T00:00+10:00",
"impliedVolatility": null,
"historicalImpliedVolatility": null,
"profitProbability": null,
"contracts": 1,
"premium": 0.85,
"action": "SELL",
"actionType": "PUT",
"brokerFees": 0.0,
"mark": 1
}
,
{
"transactionId": null,
"pairTransactionId": null,
"accountId": "d79ec11a-2011-4423-ba01-3af8de0a3e14",
"date": "2019-02-06T06:00+10:00",
"stockSymbol": "CVS",
"stockPrice": 0.0,
"strikePrice": 64.0,
"expiryDate": "2019-02-15T00:00+10:00",
"impliedVolatility": null,
"historicalImpliedVolatility": null,
"profitProbability": null,
"contracts": 1,
"premium": -0.43,
"action": "BUY",
"actionType": "PUT",
"brokerFees": 0.0,
"mark": 1
},

{
"transactionId": null,
"pairTransactionId": null,
"accountId": "d79ec11a-2011-4423-ba01-3af8de0a3e14",
"date": "2019-01-29T06:00+10:00",
"stockSymbol": "PLNT",
"stockPrice": 57.86,
"strikePrice": 57.5,
"expiryDate": "2019-03-15T00:00+10:00",
"impliedVolatility": null,
"historicalImpliedVolatility": null,
"profitProbability": null,
"contracts": 1,
"premium": 3.30,
"action": "SELL",
"actionType": "PUT",
"brokerFees": 0.0,
"mark": 1
}
,
{
"transactionId": null,
"pairTransactionId": null,
"accountId": "d79ec11a-2011-4423-ba01-3af8de0a3e14",
"date": "2019-02-12T06:00+10:00",
"stockSymbol": "PLNT",
"stockPrice": 0.0,
"strikePrice": 57.5,
"expiryDate": "2019-03-15T00:00+10:00",
"impliedVolatility": null,
"historicalImpliedVolatility": null,
"profitProbability": null,
"contracts": 1,
"premium": -2.78,
"action": "BUY",
"actionType": "PUT",
"brokerFees": 0.0,
"mark": 1
},

{
"transactionId": null,
"pairTransactionId": null,
"accountId": "d79ec11a-2011-4423-ba01-3af8de0a3e14",
"date": "2019-01-30T06:00+10:00",
"stockSymbol": "AMAT",
"stockPrice": 38.83,
"strikePrice": 38.0,
"expiryDate": "2019-03-15T00:00+10:00",
"impliedVolatility": null,
"historicalImpliedVolatility": null,
"profitProbability": null,
"contracts": 1,
"premium": 1.79,
"action": "SELL",
"actionType": "PUT",
"brokerFees": 0.0,
"mark": 1
}
,
{
"transactionId": null,
"pairTransactionId": null,
"accountId": "d79ec11a-2011-4423-ba01-3af8de0a3e14",
"date": "2019-02-12T06:00+10:00",
"stockSymbol": "AMAT",
"stockPrice": 0.0,
"strikePrice": 38.0,
"expiryDate": "2019-03-15T00:00+10:00",
"impliedVolatility": null,
"historicalImpliedVolatility": null,
"profitProbability": null,
"contracts": 1,
"premium": -1.17,
"action": "BUY",
"actionType": "PUT",
"brokerFees": 0.0,
"mark": 1
},

{
"transactionId": null,
"pairTransactionId": null,
"accountId": "d79ec11a-2011-4423-ba01-3af8de0a3e14",
"date": "2019-02-01T06:00+10:00",
"stockSymbol": "CIEN",
"stockPrice": 38.14,
"strikePrice": 36.0,
"expiryDate": "2019-03-15T00:00+10:00",
"impliedVolatility": null,
"historicalImpliedVolatility": null,
"profitProbability": null,
"contracts": 2,
"premium": 1.21,
"action": "SELL",
"actionType": "PUT",
"brokerFees": 0.0,
"mark": 1
}
,
{
"transactionId": null,
"pairTransactionId": null,
"accountId": "d79ec11a-2011-4423-ba01-3af8de0a3e14",
"date": "2019-02-13T06:00+10:00",
"stockSymbol": "CIEN",
"stockPrice": 0.0,
"strikePrice": 36.0,
"expiryDate": "2019-03-15T00:00+10:00",
"impliedVolatility": null,
"historicalImpliedVolatility": null,
"profitProbability": null,
"contracts": 2,
"premium": -0.84,
"action": "BUY",
"actionType": "PUT",
"brokerFees": 0.0,
"mark": 1
},

{
"transactionId": null,
"pairTransactionId": null,
"accountId": "d79ec11a-2011-4423-ba01-3af8de0a3e14",
"date": "2019-02-01T06:00+10:00",
"stockSymbol": "BERY",
"stockPrice": 50.31,
"strikePrice": 50.0,
"expiryDate": "2019-03-15T00:00+10:00",
"impliedVolatility": null,
"historicalImpliedVolatility": null,
"profitProbability": null,
"contracts": 1,
"premium": 1.50,
"action": "SELL",
"actionType": "PUT",
"brokerFees": 0.0,
"mark": 1
}
,
{
"transactionId": null,
"pairTransactionId": null,
"accountId": "d79ec11a-2011-4423-ba01-3af8de0a3e14",
"date": "2019-02-15T06:00+10:00",
"stockSymbol": "BERY",
"stockPrice": 0.0,
"strikePrice": 50.0,
"expiryDate": "2019-03-15T00:00+10:00",
"impliedVolatility": null,
"historicalImpliedVolatility": null,
"profitProbability": null,
"contracts": 1,
"premium": -0.75,
"action": "BUY",
"actionType": "PUT",
"brokerFees": 0.0,
"mark": 1
},

{
"transactionId": null,
"pairTransactionId": null,
"accountId": "d79ec11a-2011-4423-ba01-3af8de0a3e14",
"date": "2019-02-05T06:00+10:00",
"stockSymbol": "CRUS",
"stockPrice": 37.71,
"strikePrice": 35.0,
"expiryDate": "2019-03-15T00:00+10:00",
"impliedVolatility": null,
"historicalImpliedVolatility": null,
"profitProbability": null,
"contracts": 1,
"premium": 0.75,
"action": "SELL",
"actionType": "PUT",
"brokerFees": 0.0,
"mark": 1
}
,
{
"transactionId": null,
"pairTransactionId": null,
"accountId": "d79ec11a-2011-4423-ba01-3af8de0a3e14",
"date": "2019-02-13T06:00+10:00",
"stockSymbol": "CRUS",
"stockPrice": 0.0,
"strikePrice": 35.0,
"expiryDate": "2019-03-15T00:00+10:00",
"impliedVolatility": null,
"historicalImpliedVolatility": null,
"profitProbability": null,
"contracts": 1,
"premium": -0.50,
"action": "BUY",
"actionType": "PUT",
"brokerFees": 0.0,
"mark": 1
},

{
"transactionId": null,
"pairTransactionId": null,
"accountId": "d79ec11a-2011-4423-ba01-3af8de0a3e14",
"date": "2019-02-05T06:00+10:00",
"stockSymbol": "CSX",
"stockPrice": 67.05,
"strikePrice": 65.0,
"expiryDate": "2019-03-15T00:00+10:00",
"impliedVolatility": null,
"historicalImpliedVolatility": null,
"profitProbability": null,
"contracts": 1,
"premium": 1.13,
"action": "SELL",
"actionType": "PUT",
"brokerFees": 0.0,
"mark": 1
}
,
{
"transactionId": null,
"pairTransactionId": null,
"accountId": "d79ec11a-2011-4423-ba01-3af8de0a3e14",
"date": "2019-02-12T06:00+10:00",
"stockSymbol": "CSX",
"stockPrice": 0.0,
"strikePrice": 65.0,
"expiryDate": "2019-03-15T00:00+10:00",
"impliedVolatility": null,
"historicalImpliedVolatility": null,
"profitProbability": null,
"contracts": 1,
"premium": -0.58,
"action": "BUY",
"actionType": "PUT",
"brokerFees": 0.0,
"mark": 1
},

{
"transactionId": null,
"pairTransactionId": null,
"accountId": "d79ec11a-2011-4423-ba01-3af8de0a3e14",
"date": "2019-02-06T06:00+10:00",
"stockSymbol": "LEN",
"stockPrice": 46.86,
"strikePrice": 45.0,
"expiryDate": "2019-03-15T00:00+10:00",
"impliedVolatility": null,
"historicalImpliedVolatility": null,
"profitProbability": null,
"contracts": 1,
"premium": 1.00,
"action": "SELL",
"actionType": "PUT",
"brokerFees": 0.0,
"mark": 1
}
,
{
"transactionId": null,
"pairTransactionId": null,
"accountId": "d79ec11a-2011-4423-ba01-3af8de0a3e14",
"date": "2019-02-13T06:00+10:00",
"stockSymbol": "LEN",
"stockPrice": 0.0,
"strikePrice": 45.0,
"expiryDate": "2019-03-15T00:00+10:00",
"impliedVolatility": null,
"historicalImpliedVolatility": null,
"profitProbability": null,
"contracts": 1,
"premium": -0.50,
"action": "BUY",
"actionType": "PUT",
"brokerFees": 0.0,
"mark": 1
},

{
"transactionId": null,
"pairTransactionId": null,
"accountId": "d79ec11a-2011-4423-ba01-3af8de0a3e14",
"date": "2019-02-07T06:00+10:00",
"stockSymbol": "CVS",
"stockPrice": 66.06,
"strikePrice": 65.0,
"expiryDate": "2019-03-15T00:00+10:00",
"impliedVolatility": null,
"historicalImpliedVolatility": null,
"profitProbability": null,
"contracts": 1,
"premium": 1.71,
"action": "SELL",
"actionType": "PUT",
"brokerFees": 0.0,
"mark": 1
}
,
{
"transactionId": null,
"pairTransactionId": null,
"accountId": "d79ec11a-2011-4423-ba01-3af8de0a3e14",
"date": "2019-02-16T06:00+10:00",
"stockSymbol": "CVS",
"stockPrice": 0.0,
"strikePrice": 65.0,
"expiryDate": "2019-03-15T00:00+10:00",
"impliedVolatility": null,
"historicalImpliedVolatility": null,
"profitProbability": null,
"contracts": 1,
"premium": -0.74,
"action": "BUY",
"actionType": "PUT",
"brokerFees": 0.0,
"mark": 1
},

{
"transactionId": null,
"pairTransactionId": null,
"accountId": "d79ec11a-2011-4423-ba01-3af8de0a3e14",
"date": "2019-02-07T06:00+10:00",
"stockSymbol": "GPS",
"stockPrice": 24.76,
"strikePrice": 24.0,
"expiryDate": "2019-03-15T00:00+10:00",
"impliedVolatility": null,
"historicalImpliedVolatility": null,
"profitProbability": null,
"contracts": 1,
"premium": 1.10,
"action": "SELL",
"actionType": "PUT",
"brokerFees": 0.0,
"mark": 1
}
,
{
"transactionId": null,
"pairTransactionId": null,
"accountId": "d79ec11a-2011-4423-ba01-3af8de0a3e14",
"date": "2019-02-16T06:00+10:00",
"stockSymbol": "GPS",
"stockPrice": 0.0,
"strikePrice": 24.0,
"expiryDate": "2019-03-15T00:00+10:00",
"impliedVolatility": null,
"historicalImpliedVolatility": null,
"profitProbability": null,
"contracts": 1,
"premium": -0.90,
"action": "BUY",
"actionType": "PUT",
"brokerFees": 0.0,
"mark": 1
},

{
"transactionId": null,
"pairTransactionId": null,
"accountId": "d79ec11a-2011-4423-ba01-3af8de0a3e14",
"date": "2019-02-12T06:00+10:00",
"stockSymbol": "HIIQ",
"stockPrice": 38.37,
"strikePrice": 42.0,
"expiryDate": "2019-03-15T00:00+10:00",
"impliedVolatility": null,
"historicalImpliedVolatility": null,
"profitProbability": null,
"contracts": 1,
"premium": 3.00,
"action": "SELL",
"actionType": "CALL",
"brokerFees": 0.0,
"mark": 1
}
,
{
"transactionId": null,
"pairTransactionId": null,
"accountId": "d79ec11a-2011-4423-ba01-3af8de0a3e14",
"date": "2019-03-02T06:00+10:00",
"stockSymbol": "HIIQ",
"stockPrice": 0.0,
"strikePrice": 42.0,
"expiryDate": "2019-03-15T00:00+10:00",
"impliedVolatility": null,
"historicalImpliedVolatility": null,
"profitProbability": null,
"contracts": 1,
"premium": -2.40,
"action": "BUY",
"actionType": "CALL",
"brokerFees": 0.0,
"mark": 1
},

{
"transactionId": null,
"pairTransactionId": null,
"accountId": "d79ec11a-2011-4423-ba01-3af8de0a3e14",
"date": "2019-02-15T06:00+10:00",
"stockSymbol": "TWTR",
"stockPrice": 31.10,
"strikePrice": 30.0,
"expiryDate": "2019-03-15T00:00+10:00",
"impliedVolatility": null,
"historicalImpliedVolatility": null,
"profitProbability": null,
"contracts": 1,
"premium": 0.87,
"action": "SELL",
"actionType": "PUT",
"brokerFees": 0.0,
"mark": 1
}
,
{
"transactionId": null,
"pairTransactionId": null,
"accountId": "d79ec11a-2011-4423-ba01-3af8de0a3e14",
"date": "2019-02-26T06:00+10:00",
"stockSymbol": "TWTR",
"stockPrice": 0.0,
"strikePrice": 30.0,
"expiryDate": "2019-03-15T00:00+10:00",
"impliedVolatility": null,
"historicalImpliedVolatility": null,
"profitProbability": null,
"contracts": 1,
"premium": -0.35,
"action": "BUY",
"actionType": "PUT",
"brokerFees": 0.0,
"mark": 1
},

{
"transactionId": null,
"pairTransactionId": null,
"accountId": "d79ec11a-2011-4423-ba01-3af8de0a3e14",
"date": "2019-02-16T06:00+10:00",
"stockSymbol": "WBA",
"stockPrice": 73.35,
"strikePrice": 72.5,
"expiryDate": "2019-03-15T00:00+10:00",
"impliedVolatility": null,
"historicalImpliedVolatility": null,
"profitProbability": null,
"contracts": 1,
"premium": 1.20,
"action": "SELL",
"actionType": "PUT",
"brokerFees": 0.0,
"mark": 1
}
,
{
"transactionId": null,
"pairTransactionId": null,
"accountId": "d79ec11a-2011-4423-ba01-3af8de0a3e14",
"date": "2019-03-06T06:00+10:00",
"stockSymbol": "WBA",
"stockPrice": 0.0,
"strikePrice": 72.5,
"expiryDate": "2019-03-15T00:00+10:00",
"impliedVolatility": null,
"historicalImpliedVolatility": null,
"profitProbability": null,
"contracts": 1,
"premium": 0.00,
"action": "BUY",
"actionType": "PUT",
"brokerFees": 0.0,
"mark": 1
},

{
"transactionId": null,
"pairTransactionId": null,
"accountId": "d79ec11a-2011-4423-ba01-3af8de0a3e14",
"date": "2019-02-16T06:00+10:00",
"stockSymbol": "WGO",
"stockPrice": 31.68,
"strikePrice": 35.0,
"expiryDate": "2019-03-15T00:00+10:00",
"impliedVolatility": null,
"historicalImpliedVolatility": null,
"profitProbability": null,
"contracts": 1,
"premium": 3.70,
"action": "SELL",
"actionType": "PUT",
"brokerFees": 0.0,
"mark": 1
}
,
{
"transactionId": null,
"pairTransactionId": null,
"accountId": "d79ec11a-2011-4423-ba01-3af8de0a3e14",
"date": "2019-02-26T06:00+10:00",
"stockSymbol": "WGO",
"stockPrice": 0.0,
"strikePrice": 35.0,
"expiryDate": "2019-03-15T00:00+10:00",
"impliedVolatility": null,
"historicalImpliedVolatility": null,
"profitProbability": null,
"contracts": 1,
"premium": -1.75,
"action": "BUY",
"actionType": "PUT",
"brokerFees": 0.0,
"mark": 1
},

{
"transactionId": null,
"pairTransactionId": null,
"accountId": "d79ec11a-2011-4423-ba01-3af8de0a3e14",
"date": "2019-02-20T06:00+10:00",
"stockSymbol": "BMCH",
"stockPrice": 18.15,
"strikePrice": 17.5,
"expiryDate": "2019-04-18T00:00+10:00",
"impliedVolatility": null,
"historicalImpliedVolatility": null,
"profitProbability": null,
"contracts": 3,
"premium": 0.70,
"action": "SELL",
"actionType": "PUT",
"brokerFees": 0.0,
"mark": 1
}
,
{
"transactionId": null,
"pairTransactionId": null,
"accountId": "d79ec11a-2011-4423-ba01-3af8de0a3e14",
"date": "2019-03-01T06:00+10:00",
"stockSymbol": "BMCH",
"stockPrice": 0.0,
"strikePrice": 17.5,
"expiryDate": "2019-04-18T00:00+10:00",
"impliedVolatility": null,
"historicalImpliedVolatility": null,
"profitProbability": null,
"contracts": 3,
"premium": -0.35,
"action": "BUY",
"actionType": "PUT",
"brokerFees": 0.0,
"mark": 1
},

{
"transactionId": null,
"pairTransactionId": null,
"accountId": "d79ec11a-2011-4423-ba01-3af8de0a3e14",
"date": "2019-02-20T06:00+10:00",
"stockSymbol": "CSX",
"stockPrice": 72.65,
"strikePrice": 70.0,
"expiryDate": "2019-04-18T00:00+10:00",
"impliedVolatility": null,
"historicalImpliedVolatility": null,
"profitProbability": null,
"contracts": 1,
"premium": 1.60,
"action": "SELL",
"actionType": "PUT",
"brokerFees": 0.0,
"mark": 1
}
,
{
"transactionId": null,
"pairTransactionId": null,
"accountId": "d79ec11a-2011-4423-ba01-3af8de0a3e14",
"date": "2019-03-06T06:00+10:00",
"stockSymbol": "CSX",
"stockPrice": 0.0,
"strikePrice": 70.0,
"expiryDate": "2019-04-18T00:00+10:00",
"impliedVolatility": null,
"historicalImpliedVolatility": null,
"profitProbability": null,
"contracts": 1,
"premium": -1.29,
"action": "BUY",
"actionType": "PUT",
"brokerFees": 0.0,
"mark": 1
},

{
"transactionId": null,
"pairTransactionId": null,
"accountId": "d79ec11a-2011-4423-ba01-3af8de0a3e14",
"date": "2019-02-20T06:00+10:00",
"stockSymbol": "VZ",
"stockPrice": 55.57,
"strikePrice": 55.0,
"expiryDate": "2019-04-18T00:00+10:00",
"impliedVolatility": null,
"historicalImpliedVolatility": null,
"profitProbability": null,
"contracts": 1,
"premium": 1.30,
"action": "SELL",
"actionType": "PUT",
"brokerFees": 0.0,
"mark": 1
}
,
{
"transactionId": null,
"pairTransactionId": null,
"accountId": "d79ec11a-2011-4423-ba01-3af8de0a3e14",
"date": "2019-02-26T06:00+10:00",
"stockSymbol": "VZ",
"stockPrice": 0.0,
"strikePrice": 55.0,
"expiryDate": "2019-04-18T00:00+10:00",
"impliedVolatility": null,
"historicalImpliedVolatility": null,
"profitProbability": null,
"contracts": 1,
"premium": -0.78,
"action": "BUY",
"actionType": "PUT",
"brokerFees": 0.0,
"mark": 1
},

{
"transactionId": null,
"pairTransactionId": null,
"accountId": "d79ec11a-2011-4423-ba01-3af8de0a3e14",
"date": "2019-02-26T06:00+10:00",
"stockSymbol": "EXEL",
"stockPrice": 22.37,
"strikePrice": 22.0,
"expiryDate": "2019-04-18T00:00+10:00",
"impliedVolatility": null,
"historicalImpliedVolatility": null,
"profitProbability": null,
"contracts": 3,
"premium": 1.30,
"action": "SELL",
"actionType": "PUT",
"brokerFees": 0.0,
"mark": 1
}
,
{
"transactionId": null,
"pairTransactionId": null,
"accountId": "d79ec11a-2011-4423-ba01-3af8de0a3e14",
"date": "2019-03-13T06:00+10:00",
"stockSymbol": "EXEL",
"stockPrice": 0.0,
"strikePrice": 22.0,
"expiryDate": "2019-04-18T00:00+10:00",
"impliedVolatility": null,
"historicalImpliedVolatility": null,
"profitProbability": null,
"contracts": 3,
"premium": -0.60,
"action": "BUY",
"actionType": "PUT",
"brokerFees": 0.0,
"mark": 1
},

{
"transactionId": null,
"pairTransactionId": null,
"accountId": "d79ec11a-2011-4423-ba01-3af8de0a3e14",
"date": "2019-02-27T06:00+10:00",
"stockSymbol": "WFC",
"stockPrice": 49.67,
"strikePrice": 50.0,
"expiryDate": "2019-04-18T00:00+10:00",
"impliedVolatility": null,
"historicalImpliedVolatility": null,
"profitProbability": null,
"contracts": 1,
"premium": 1.52,
"action": "SELL",
"actionType": "PUT",
"brokerFees": 0.0,
"mark": 1
}
,
{
"transactionId": null,
"pairTransactionId": null,
"accountId": "d79ec11a-2011-4423-ba01-3af8de0a3e14",
"date": "2019-03-16T06:00+10:00",
"stockSymbol": "WFC",
"stockPrice": 0.0,
"strikePrice": 50.0,
"expiryDate": "2019-04-18T00:00+10:00",
"impliedVolatility": null,
"historicalImpliedVolatility": null,
"profitProbability": null,
"contracts": 1,
"premium": -0.86,
"action": "BUY",
"actionType": "PUT",
"brokerFees": 0.0,
"mark": 1
},

{
"transactionId": null,
"pairTransactionId": null,
"accountId": "d79ec11a-2011-4423-ba01-3af8de0a3e14",
"date": "2019-03-01T06:00+10:00",
"stockSymbol": "TWTR",
"stockPrice": 30.67,
"strikePrice": 30.0,
"expiryDate": "2019-04-18T00:00+10:00",
"impliedVolatility": null,
"historicalImpliedVolatility": null,
"profitProbability": null,
"contracts": 3,
"premium": 1.35,
"action": "SELL",
"actionType": "PUT",
"brokerFees": 0.0,
"mark": 1
}
,
{
"transactionId": null,
"pairTransactionId": null,
"accountId": "d79ec11a-2011-4423-ba01-3af8de0a3e14",
"date": "2019-03-13T06:00+10:00",
"stockSymbol": "TWTR",
"stockPrice": 0.0,
"strikePrice": 30.0,
"expiryDate": "2019-04-18T00:00+10:00",
"impliedVolatility": null,
"historicalImpliedVolatility": null,
"profitProbability": null,
"contracts": 3,
"premium": -0.84,
"action": "BUY",
"actionType": "PUT",
"brokerFees": 0.0,
"mark": 1
},

{
"transactionId": null,
"pairTransactionId": null,
"accountId": "d79ec11a-2011-4423-ba01-3af8de0a3e14",
"date": "2019-03-01T06:00+10:00",
"stockSymbol": "VZ",
"stockPrice": 57.11,
"strikePrice": 55.0,
"expiryDate": "2019-04-18T00:00+10:00",
"impliedVolatility": null,
"historicalImpliedVolatility": null,
"profitProbability": null,
"contracts": 1,
"premium": 0.67,
"action": "SELL",
"actionType": "PUT",
"brokerFees": 0.0,
"mark": 1
}
,
{
"transactionId": null,
"pairTransactionId": null,
"accountId": "d79ec11a-2011-4423-ba01-3af8de0a3e14",
"date": "2019-03-13T06:00+10:00",
"stockSymbol": "VZ",
"stockPrice": 0.0,
"strikePrice": 55.0,
"expiryDate": "2019-04-18T00:00+10:00",
"impliedVolatility": null,
"historicalImpliedVolatility": null,
"profitProbability": null,
"contracts": 1,
"premium": -0.46,
"action": "BUY",
"actionType": "PUT",
"brokerFees": 0.0,
"mark": 1
},

{
"transactionId": null,
"pairTransactionId": null,
"accountId": "d79ec11a-2011-4423-ba01-3af8de0a3e14",
"date": "2019-03-01T06:00+10:00",
"stockSymbol": "KO",
"stockPrice": 45.55,
"strikePrice": 45.0,
"expiryDate": "2019-04-18T00:00+10:00",
"impliedVolatility": null,
"historicalImpliedVolatility": null,
"profitProbability": null,
"contracts": 1,
"premium": 0.71,
"action": "SELL",
"actionType": "PUT",
"brokerFees": 0.0,
"mark": 1
}
,
{
"transactionId": null,
"pairTransactionId": null,
"accountId": "d79ec11a-2011-4423-ba01-3af8de0a3e14",
"date": "2019-03-06T06:00+10:00",
"stockSymbol": "KO",
"stockPrice": 0.0,
"strikePrice": 45.0,
"expiryDate": "2019-04-18T00:00+10:00",
"impliedVolatility": null,
"historicalImpliedVolatility": null,
"profitProbability": null,
"contracts": 1,
"premium": -0.64,
"action": "BUY",
"actionType": "PUT",
"brokerFees": 0.0,
"mark": 1
},

{
"transactionId": null,
"pairTransactionId": null,
"accountId": "d79ec11a-2011-4423-ba01-3af8de0a3e14",
"date": "2019-03-02T06:00+10:00",
"stockSymbol": "APOG",
"stockPrice": 36.14,
"strikePrice": 35.0,
"expiryDate": "2019-04-18T00:00+10:00",
"impliedVolatility": null,
"historicalImpliedVolatility": null,
"profitProbability": null,
"contracts": 1,
"premium": 1.65,
"action": "SELL",
"actionType": "PUT",
"brokerFees": 0.0,
"mark": 1
}
,
{
"transactionId": null,
"pairTransactionId": null,
"accountId": "d79ec11a-2011-4423-ba01-3af8de0a3e14",
"date": "2019-03-15T06:00+10:00",
"stockSymbol": "APOG",
"stockPrice": 0.0,
"strikePrice": 35.0,
"expiryDate": "2019-04-18T00:00+10:00",
"impliedVolatility": null,
"historicalImpliedVolatility": null,
"profitProbability": null,
"contracts": 1,
"premium": -1.50,
"action": "BUY",
"actionType": "PUT",
"brokerFees": 0.0,
"mark": 1
},

{
"transactionId": null,
"pairTransactionId": null,
"accountId": "d79ec11a-2011-4423-ba01-3af8de0a3e14",
"date": "2019-03-02T06:00+10:00",
"stockSymbol": "HIIQ",
"stockPrice": 37.21,
"strikePrice": 40.0,
"expiryDate": "2019-04-18T00:00+10:00",
"impliedVolatility": null,
"historicalImpliedVolatility": null,
"profitProbability": null,
"contracts": 1,
"premium": 4.30,
"action": "SELL",
"actionType": "CALL",
"brokerFees": 0.0,
"mark": 1
}
,
{
"transactionId": null,
"pairTransactionId": null,
"accountId": "d79ec11a-2011-4423-ba01-3af8de0a3e14",
"date": "2019-03-13T06:00+10:00",
"stockSymbol": "HIIQ",
"stockPrice": 0.0,
"strikePrice": 40.0,
"expiryDate": "2019-04-18T00:00+10:00",
"impliedVolatility": null,
"historicalImpliedVolatility": null,
"profitProbability": null,
"contracts": 1,
"premium": -2.85,
"action": "BUY",
"actionType": "CALL",
"brokerFees": 0.0,
"mark": 1
},

{
"transactionId": null,
"pairTransactionId": null,
"accountId": "d79ec11a-2011-4423-ba01-3af8de0a3e14",
"date": "2019-03-05T06:00+10:00",
"stockSymbol": "TOL",
"stockPrice": 36.79,
"strikePrice": 35.0,
"expiryDate": "2019-04-18T00:00+10:00",
"impliedVolatility": null,
"historicalImpliedVolatility": null,
"profitProbability": null,
"contracts": 1,
"premium": 1.03,
"action": "SELL",
"actionType": "PUT",
"brokerFees": 0.0,
"mark": 1
}
,
{
"transactionId": null,
"pairTransactionId": null,
"accountId": "d79ec11a-2011-4423-ba01-3af8de0a3e14",
"date": "2019-03-19T06:00+10:00",
"stockSymbol": "TOL",
"stockPrice": 0.0,
"strikePrice": 35.0,
"expiryDate": "2019-04-18T00:00+10:00",
"impliedVolatility": null,
"historicalImpliedVolatility": null,
"profitProbability": null,
"contracts": 1,
"premium": -0.68,
"action": "BUY",
"actionType": "PUT",
"brokerFees": 0.0,
"mark": 1
},

{
"transactionId": null,
"pairTransactionId": null,
"accountId": "d79ec11a-2011-4423-ba01-3af8de0a3e14",
"date": "2019-03-05T06:00+10:00",
"stockSymbol": "KEM",
"stockPrice": 18.97,
"strikePrice": 18.0,
"expiryDate": "2019-04-18T00:00+10:00",
"impliedVolatility": null,
"historicalImpliedVolatility": null,
"profitProbability": null,
"contracts": 3,
"premium": 0.75,
"action": "SELL",
"actionType": "PUT",
"brokerFees": 0.0,
"mark": 1
}
,
{
"transactionId": null,
"pairTransactionId": null,
"accountId": "d79ec11a-2011-4423-ba01-3af8de0a3e14",
"date": "2019-04-04T06:00+10:00",
"stockSymbol": "KEM",
"stockPrice": 0.0,
"strikePrice": 18.0,
"expiryDate": "2019-04-18T00:00+10:00",
"impliedVolatility": null,
"historicalImpliedVolatility": null,
"profitProbability": null,
"contracts": 3,
"premium": -0.55,
"action": "BUY",
"actionType": "PUT",
"brokerFees": -0.17,
"mark": 1
},

{
"transactionId": null,
"pairTransactionId": null,
"accountId": "d79ec11a-2011-4423-ba01-3af8de0a3e14",
"date": "2019-03-05T06:00+10:00",
"stockSymbol": "BCC",
"stockPrice": 27.96,
"strikePrice": 27.5,
"expiryDate": "2019-04-18T00:00+10:00",
"impliedVolatility": null,
"historicalImpliedVolatility": null,
"profitProbability": null,
"contracts": 2,
"premium": 1.00,
"action": "SELL",
"actionType": "PUT",
"brokerFees": 0.0,
"mark": 1
}
,
{
"transactionId": null,
"pairTransactionId": null,
"accountId": "d79ec11a-2011-4423-ba01-3af8de0a3e14",
"date": "2019-04-06T06:00+10:00",
"stockSymbol": "BCC",
"stockPrice": 0.0,
"strikePrice": 27.5,
"expiryDate": "2019-04-18T00:00+10:00",
"impliedVolatility": null,
"historicalImpliedVolatility": null,
"profitProbability": null,
"contracts": 2,
"premium": -0.50,
"action": "BUY",
"actionType": "PUT",
"brokerFees": 3.29,
"mark": 1
},

{
"transactionId": null,
"pairTransactionId": null,
"accountId": "d79ec11a-2011-4423-ba01-3af8de0a3e14",
"date": "2019-03-06T06:00+10:00",
"stockSymbol": "WBA",
"stockPrice": 63.63,
"strikePrice": 72.5,
"expiryDate": "2019-04-18T00:00+10:00",
"impliedVolatility": null,
"historicalImpliedVolatility": null,
"profitProbability": null,
"contracts": 1,
"premium": 0.20,
"action": "SELL",
"actionType": "CALL",
"brokerFees": 0.0,
"mark": 1
}
,
{
"transactionId": null,
"pairTransactionId": null,
"accountId": "d79ec11a-2011-4423-ba01-3af8de0a3e14",
"date": "2019-03-07T06:00+10:00",
"stockSymbol": "WBA",
"stockPrice": 0.0,
"strikePrice": 72.5,
"expiryDate": "2019-04-18T00:00+10:00",
"impliedVolatility": null,
"historicalImpliedVolatility": null,
"profitProbability": null,
"contracts": 1,
"premium": -0.11,
"action": "BUY",
"actionType": "CALL",
"brokerFees": 0.0,
"mark": 1
},

{
"transactionId": null,
"pairTransactionId": null,
"accountId": "d79ec11a-2011-4423-ba01-3af8de0a3e14",
"date": "2019-03-07T06:00+10:00",
"stockSymbol": "WBA",
"stockPrice": 61.37,
"strikePrice": 70.0,
"expiryDate": "2019-04-18T00:00+10:00",
"impliedVolatility": null,
"historicalImpliedVolatility": null,
"profitProbability": null,
"contracts": 1,
"premium": 0.23,
"action": "SELL",
"actionType": "CALL",
"brokerFees": 0.0,
"mark": 1
}
,
{
"transactionId": null,
"pairTransactionId": null,
"accountId": "d79ec11a-2011-4423-ba01-3af8de0a3e14",
"date": "2019-04-03T06:00+10:00",
"stockSymbol": "WBA",
"stockPrice": 0.0,
"strikePrice": 70.0,
"expiryDate": "2019-04-18T00:00+10:00",
"impliedVolatility": null,
"historicalImpliedVolatility": null,
"profitProbability": null,
"contracts": 1,
"premium": -0.01,
"action": "BUY",
"actionType": "CALL",
"brokerFees": 0.0,
"mark": 1
},

{
"transactionId": null,
"pairTransactionId": null,
"accountId": "d79ec11a-2011-4423-ba01-3af8de0a3e14",
"date": "2019-03-08T06:00+10:00",
"stockSymbol": "LEN",
"stockPrice": 47.60,
"strikePrice": 45.0,
"expiryDate": "2019-04-18T00:00+10:00",
"impliedVolatility": null,
"historicalImpliedVolatility": null,
"profitProbability": null,
"contracts": 1,
"premium": 1.21,
"action": "SELL",
"actionType": "PUT",
"brokerFees": 0.0,
"mark": 1
}
,
{
"transactionId": null,
"pairTransactionId": null,
"accountId": "d79ec11a-2011-4423-ba01-3af8de0a3e14",
"date": "2019-03-19T06:00+10:00",
"stockSymbol": "LEN",
"stockPrice": 0.0,
"strikePrice": 45.0,
"expiryDate": "2019-04-18T00:00+10:00",
"impliedVolatility": null,
"historicalImpliedVolatility": null,
"profitProbability": null,
"contracts": 1,
"premium": -0.79,
"action": "BUY",
"actionType": "PUT",
"brokerFees": 0.0,
"mark": 1
},

{
"transactionId": null,
"pairTransactionId": null,
"accountId": "d79ec11a-2011-4423-ba01-3af8de0a3e14",
"date": "2019-03-08T06:00+10:00",
"stockSymbol": "WGO",
"stockPrice": 31.18,
"strikePrice": 30.0,
"expiryDate": "2019-04-18T00:00+10:00",
"impliedVolatility": null,
"historicalImpliedVolatility": null,
"profitProbability": null,
"contracts": 2,
"premium": 1.70,
"action": "SELL",
"actionType": "PUT",
"brokerFees": 0.0,
"mark": 1
}
,
{
"transactionId": null,
"pairTransactionId": null,
"accountId": "d79ec11a-2011-4423-ba01-3af8de0a3e14",
"date": "2019-03-15T06:00+10:00",
"stockSymbol": "WGO",
"stockPrice": 0.0,
"strikePrice": 30.0,
"expiryDate": "2019-04-18T00:00+10:00",
"impliedVolatility": null,
"historicalImpliedVolatility": null,
"profitProbability": null,
"contracts": 2,
"premium": -1.55,
"action": "BUY",
"actionType": "PUT",
"brokerFees": 0.0,
"mark": 1
},

{
"transactionId": null,
"pairTransactionId": null,
"accountId": "d79ec11a-2011-4423-ba01-3af8de0a3e14",
"date": "2019-03-08T06:00+10:00",
"stockSymbol": "GNTX",
"stockPrice": 20.47,
"strikePrice": 20.0,
"expiryDate": "2019-04-18T00:00+10:00",
"impliedVolatility": null,
"historicalImpliedVolatility": null,
"profitProbability": null,
"contracts": 3,
"premium": 0.53,
"action": "SELL",
"actionType": "PUT",
"brokerFees": 0.0,
"mark": 1
}
,
{
"transactionId": null,
"pairTransactionId": null,
"accountId": "d79ec11a-2011-4423-ba01-3af8de0a3e14",
"date": "2019-03-16T06:00+10:00",
"stockSymbol": "GNTX",
"stockPrice": 0.0,
"strikePrice": 20.0,
"expiryDate": "2019-04-18T00:00+10:00",
"impliedVolatility": null,
"historicalImpliedVolatility": null,
"profitProbability": null,
"contracts": 3,
"premium": -0.35,
"action": "BUY",
"actionType": "PUT",
"brokerFees": 0.0,
"mark": 1
},

{
"transactionId": null,
"pairTransactionId": null,
"accountId": "d79ec11a-2011-4423-ba01-3af8de0a3e14",
"date": "2019-03-09T06:00+10:00",
"stockSymbol": "AMAT",
"stockPrice": 37.64,
"strikePrice": 37.0,
"expiryDate": "2019-04-18T00:00+10:00",
"impliedVolatility": null,
"historicalImpliedVolatility": null,
"profitProbability": null,
"contracts": 2,
"premium": 1.31,
"action": "SELL",
"actionType": "PUT",
"brokerFees": 0.0,
"mark": 1
}
,
{
"transactionId": null,
"pairTransactionId": null,
"accountId": "d79ec11a-2011-4423-ba01-3af8de0a3e14",
"date": "2019-03-14T06:00+10:00",
"stockSymbol": "AMAT",
"stockPrice": 0.0,
"strikePrice": 37.0,
"expiryDate": "2019-04-18T00:00+10:00",
"impliedVolatility": null,
"historicalImpliedVolatility": null,
"profitProbability": null,
"contracts": 2,
"premium": -0.73,
"action": "BUY",
"actionType": "PUT",
"brokerFees": 0.0,
"mark": 1
},

{
"transactionId": null,
"pairTransactionId": null,
"accountId": "d79ec11a-2011-4423-ba01-3af8de0a3e14",
"date": "2019-03-12T06:00+10:00",
"stockSymbol": "TDS",
"stockPrice": 31.96,
"strikePrice": 30.0,
"expiryDate": "2019-04-18T00:00+10:00",
"impliedVolatility": null,
"historicalImpliedVolatility": null,
"profitProbability": null,
"contracts": 1,
"premium": 0.50,
"action": "SELL",
"actionType": "PUT",
"brokerFees": 0.0,
"mark": 1
}
,
{
"transactionId": null,
"pairTransactionId": null,
"accountId": "d79ec11a-2011-4423-ba01-3af8de0a3e14",
"date": "2019-03-16T06:00+10:00",
"stockSymbol": "TDS",
"stockPrice": 0.0,
"strikePrice": 30.0,
"expiryDate": "2019-04-18T00:00+10:00",
"impliedVolatility": null,
"historicalImpliedVolatility": null,
"profitProbability": null,
"contracts": 1,
"premium": -0.38,
"action": "BUY",
"actionType": "PUT",
"brokerFees": 0.0,
"mark": 1
},

{
"transactionId": null,
"pairTransactionId": null,
"accountId": "d79ec11a-2011-4423-ba01-3af8de0a3e14",
"date": "2019-03-12T06:00+10:00",
"stockSymbol": "AEIS",
"stockPrice": 47.86,
"strikePrice": 45.0,
"expiryDate": "2019-04-18T00:00+10:00",
"impliedVolatility": null,
"historicalImpliedVolatility": null,
"profitProbability": null,
"contracts": 1,
"premium": 1.08,
"action": "SELL",
"actionType": "PUT",
"brokerFees": 0.0,
"mark": 1
}
,
{
"transactionId": null,
"pairTransactionId": null,
"accountId": "d79ec11a-2011-4423-ba01-3af8de0a3e14",
"date": "2019-03-19T06:00+10:00",
"stockSymbol": "AEIS",
"stockPrice": 0.0,
"strikePrice": 45.0,
"expiryDate": "2019-04-18T00:00+10:00",
"impliedVolatility": null,
"historicalImpliedVolatility": null,
"profitProbability": null,
"contracts": 1,
"premium": -0.72,
"action": "BUY",
"actionType": "PUT",
"brokerFees": 0.0,
"mark": 1
},

{
"transactionId": null,
"pairTransactionId": null,
"accountId": "d79ec11a-2011-4423-ba01-3af8de0a3e14",
"date": "2019-03-12T06:00+10:00",
"stockSymbol": "HPQ",
"stockPrice": 19.03,
"strikePrice": 18.0,
"expiryDate": "2019-04-18T00:00+10:00",
"impliedVolatility": null,
"historicalImpliedVolatility": null,
"profitProbability": null,
"contracts": 3,
"premium": 0.21,
"action": "SELL",
"actionType": "PUT",
"brokerFees": 0.0,
"mark": 1
}
,
{
"transactionId": null,
"pairTransactionId": null,
"accountId": "d79ec11a-2011-4423-ba01-3af8de0a3e14",
"date": "2019-03-14T06:00+10:00",
"stockSymbol": "HPQ",
"stockPrice": 0.0,
"strikePrice": 18.0,
"expiryDate": "2019-04-18T00:00+10:00",
"impliedVolatility": null,
"historicalImpliedVolatility": null,
"profitProbability": null,
"contracts": 3,
"premium": -0.10,
"action": "BUY",
"actionType": "PUT",
"brokerFees": 0.0,
"mark": 1
},

{
"transactionId": null,
"pairTransactionId": null,
"accountId": "d79ec11a-2011-4423-ba01-3af8de0a3e14",
"date": "2019-03-12T06:00+10:00",
"stockSymbol": "CVS",
"stockPrice": 53.80,
"strikePrice": 52.5,
"expiryDate": "2019-04-18T00:00+10:00",
"impliedVolatility": null,
"historicalImpliedVolatility": null,
"profitProbability": null,
"contracts": 1,
"premium": 1.41,
"action": "SELL",
"actionType": "PUT",
"brokerFees": 0.0,
"mark": 1
}
,
{
"transactionId": null,
"pairTransactionId": null,
"accountId": "d79ec11a-2011-4423-ba01-3af8de0a3e14",
"date": "2019-03-14T06:00+10:00",
"stockSymbol": "CVS",
"stockPrice": 0.0,
"strikePrice": 52.5,
"expiryDate": "2019-04-18T00:00+10:00",
"impliedVolatility": null,
"historicalImpliedVolatility": null,
"profitProbability": null,
"contracts": 1,
"premium": -0.55,
"action": "BUY",
"actionType": "PUT",
"brokerFees": 0.0,
"mark": 1
},

{
"transactionId": null,
"pairTransactionId": null,
"accountId": "d79ec11a-2011-4423-ba01-3af8de0a3e14",
"date": "2019-03-13T06:00+10:00",
"stockSymbol": "HIIQ",
"stockPrice": 38.52,
"strikePrice": 44.0,
"expiryDate": "2019-05-17T00:00+10:00",
"impliedVolatility": null,
"historicalImpliedVolatility": null,
"profitProbability": null,
"contracts": 1,
"premium": 3.26,
"action": "SELL",
"actionType": "CALL",
"brokerFees": 0.0,
"mark": 1
}
,
{
"transactionId": null,
"pairTransactionId": null,
"accountId": "d79ec11a-2011-4423-ba01-3af8de0a3e14",
"date": "2019-04-23T06:00+10:00",
"stockSymbol": "HIIQ",
"stockPrice": 0.0,
"strikePrice": 44.0,
"expiryDate": "2019-05-17T00:00+10:00",
"impliedVolatility": null,
"historicalImpliedVolatility": null,
"profitProbability": null,
"contracts": 1,
"premium": -0.10,
"action": "BUY",
"actionType": "CALL",
"brokerFees": 0.0,
"mark": 1
},

{
"transactionId": null,
"pairTransactionId": null,
"accountId": "d79ec11a-2011-4423-ba01-3af8de0a3e14",
"date": "2019-03-14T06:00+10:00",
"stockSymbol": "HPQ",
"stockPrice": 19.53,
"strikePrice": 19.0,
"expiryDate": "2019-04-18T00:00+10:00",
"impliedVolatility": null,
"historicalImpliedVolatility": null,
"profitProbability": null,
"contracts": 4,
"premium": 0.25,
"action": "SELL",
"actionType": "PUT",
"brokerFees": 0.0,
"mark": 1
}
,
{
"transactionId": null,
"pairTransactionId": null,
"accountId": "d79ec11a-2011-4423-ba01-3af8de0a3e14",
"date": "2019-03-19T06:00+10:00",
"stockSymbol": "HPQ",
"stockPrice": 0.0,
"strikePrice": 19.0,
"expiryDate": "2019-04-18T00:00+10:00",
"impliedVolatility": null,
"historicalImpliedVolatility": null,
"profitProbability": null,
"contracts": 4,
"premium": -0.14,
"action": "BUY",
"actionType": "PUT",
"brokerFees": 4.72,
"mark": 1
},

{
"transactionId": null,
"pairTransactionId": null,
"accountId": "d79ec11a-2011-4423-ba01-3af8de0a3e14",
"date": "2019-03-14T06:00+10:00",
"stockSymbol": "HTZ",
"stockPrice": 16.67,
"strikePrice": 19.0,
"expiryDate": "2019-03-15T00:00+10:00",
"impliedVolatility": null,
"historicalImpliedVolatility": null,
"profitProbability": null,
"contracts": 4,
"premium": 2.31,
"action": "SELL",
"actionType": "PUT",
"brokerFees": 0.0,
"mark": 1
}
,
{
"transactionId": null,
"pairTransactionId": null,
"accountId": "d79ec11a-2011-4423-ba01-3af8de0a3e14",
"date": "2019-03-16T06:00+10:00",
"stockSymbol": "HTZ",
"stockPrice": 0.0,
"strikePrice": 19.0,
"expiryDate": "2019-03-15T00:00+10:00",
"impliedVolatility": null,
"historicalImpliedVolatility": null,
"profitProbability": null,
"contracts": 4,
"premium": -2.31,
"action": "BUY",
"actionType": "PUT",
"brokerFees": 3.22,
"mark": 1
},

{
"transactionId": null,
"pairTransactionId": null,
"accountId": "d79ec11a-2011-4423-ba01-3af8de0a3e14",
"date": "2019-03-14T06:00+10:00",
"stockSymbol": "WLK",
"stockPrice": 69.30,
"strikePrice": 65.0,
"expiryDate": "2019-04-18T00:00+10:00",
"impliedVolatility": null,
"historicalImpliedVolatility": null,
"profitProbability": null,
"contracts": 1,
"premium": 0.96,
"action": "SELL",
"actionType": "PUT",
"brokerFees": 0.0,
"mark": 1
}
,
{
"transactionId": null,
"pairTransactionId": null,
"accountId": "d79ec11a-2011-4423-ba01-3af8de0a3e14",
"date": "2019-03-16T06:00+10:00",
"stockSymbol": "WLK",
"stockPrice": 0.0,
"strikePrice": 65.0,
"expiryDate": "2019-04-18T00:00+10:00",
"impliedVolatility": null,
"historicalImpliedVolatility": null,
"profitProbability": null,
"contracts": 1,
"premium": -0.95,
"action": "BUY",
"actionType": "PUT",
"brokerFees": 2.28,
"mark": 1
},

{
"transactionId": null,
"pairTransactionId": null,
"accountId": "d79ec11a-2011-4423-ba01-3af8de0a3e14",
"date": "2019-03-15T06:00+10:00",
"stockSymbol": "VZ",
"stockPrice": 57.88,
"strikePrice": 57.5,
"expiryDate": "2019-04-18T00:00+10:00",
"impliedVolatility": null,
"historicalImpliedVolatility": null,
"profitProbability": null,
"contracts": 1,
"premium": 0.96,
"action": "SELL",
"actionType": "PUT",
"brokerFees": 0.0,
"mark": 1
}
,
{
"transactionId": null,
"pairTransactionId": null,
"accountId": "d79ec11a-2011-4423-ba01-3af8de0a3e14",
"date": "2019-03-23T06:00+10:00",
"stockSymbol": "VZ",
"stockPrice": 0.0,
"strikePrice": 57.5,
"expiryDate": "2019-04-18T00:00+10:00",
"impliedVolatility": null,
"historicalImpliedVolatility": null,
"profitProbability": null,
"contracts": 1,
"premium": -0.50,
"action": "BUY",
"actionType": "PUT",
"brokerFees": 0.0,
"mark": 1
},

{
"transactionId": null,
"pairTransactionId": null,
"accountId": "d79ec11a-2011-4423-ba01-3af8de0a3e14",
"date": "2019-03-16T06:00+10:00",
"stockSymbol": "AMAT",
"stockPrice": 40.50,
"strikePrice": 39.0,
"expiryDate": "2019-04-18T00:00+10:00",
"impliedVolatility": null,
"historicalImpliedVolatility": null,
"profitProbability": null,
"contracts": 2,
"premium": 0.76,
"action": "SELL",
"actionType": "PUT",
"brokerFees": 0.0,
"mark": 1
}
,
{
"transactionId": null,
"pairTransactionId": null,
"accountId": "d79ec11a-2011-4423-ba01-3af8de0a3e14",
"date": "2019-03-22T06:00+10:00",
"stockSymbol": "AMAT",
"stockPrice": 0.0,
"strikePrice": 39.0,
"expiryDate": "2019-04-18T00:00+10:00",
"impliedVolatility": null,
"historicalImpliedVolatility": null,
"profitProbability": null,
"contracts": 2,
"premium": -0.45,
"action": "BUY",
"actionType": "PUT",
"brokerFees": 0.0,
"mark": 1
},

{
"transactionId": null,
"pairTransactionId": null,
"accountId": "d79ec11a-2011-4423-ba01-3af8de0a3e14",
"date": "2019-03-16T06:00+10:00",
"stockSymbol": "CSCO",
"stockPrice": 53.47,
"strikePrice": 52.0,
"expiryDate": "2019-04-05T00:00+10:00",
"impliedVolatility": null,
"historicalImpliedVolatility": null,
"profitProbability": null,
"contracts": 1,
"premium": 0.36,
"action": "SELL",
"actionType": "PUT",
"brokerFees": 0.79,
"mark": 1
}
,
{
"transactionId": null,
"pairTransactionId": null,
"accountId": "d79ec11a-2011-4423-ba01-3af8de0a3e14",
"date": "2019-03-30T06:00+10:00",
"stockSymbol": "CSCO",
"stockPrice": 0.0,
"strikePrice": 52.0,
"expiryDate": "2019-04-05T00:00+10:00",
"impliedVolatility": null,
"historicalImpliedVolatility": null,
"profitProbability": null,
"contracts": 1,
"premium": -0.10,
"action": "BUY",
"actionType": "PUT",
"brokerFees": 1.09,
"mark": 1
},

{
"transactionId": null,
"pairTransactionId": null,
"accountId": "d79ec11a-2011-4423-ba01-3af8de0a3e14",
"date": "2019-03-16T06:00+10:00",
"stockSymbol": "CRUS",
"stockPrice": 41.31,
"strikePrice": 40.0,
"expiryDate": "2019-04-12T00:00+10:00",
"impliedVolatility": null,
"historicalImpliedVolatility": null,
"profitProbability": null,
"contracts": 1,
"premium": 0.75,
"action": "SELL",
"actionType": "PUT",
"brokerFees": 0.34,
"mark": 1
}
,
{
"transactionId": null,
"pairTransactionId": null,
"accountId": "d79ec11a-2011-4423-ba01-3af8de0a3e14",
"date": "2019-03-22T06:00+10:00",
"stockSymbol": "CRUS",
"stockPrice": 0.0,
"strikePrice": 40.0,
"expiryDate": "2019-04-12T00:00+10:00",
"impliedVolatility": null,
"historicalImpliedVolatility": null,
"profitProbability": null,
"contracts": 1,
"premium": -0.29,
"action": "BUY",
"actionType": "PUT",
"brokerFees": 1.94,
"mark": 1
},

{
"transactionId": null,
"pairTransactionId": null,
"accountId": "d79ec11a-2011-4423-ba01-3af8de0a3e14",
"date": "2019-03-16T06:00+10:00",
"stockSymbol": "MOMO",
"stockPrice": 38.42,
"strikePrice": 35.0,
"expiryDate": "2019-04-05T00:00+10:00",
"impliedVolatility": null,
"historicalImpliedVolatility": null,
"profitProbability": null,
"contracts": 1,
"premium": 0.45,
"action": "SELL",
"actionType": "PUT",
"brokerFees": 1.08,
"mark": 1
}
,
{
"transactionId": null,
"pairTransactionId": null,
"accountId": "d79ec11a-2011-4423-ba01-3af8de0a3e14",
"date": "2019-03-20T06:00+10:00",
"stockSymbol": "MOMO",
"stockPrice": 0.0,
"strikePrice": 35.0,
"expiryDate": "2019-04-05T00:00+10:00",
"impliedVolatility": null,
"historicalImpliedVolatility": null,
"profitProbability": null,
"contracts": 1,
"premium": -0.35,
"action": "BUY",
"actionType": "PUT",
"brokerFees": 0.34,
"mark": 1
},

{
"transactionId": null,
"pairTransactionId": null,
"accountId": "d79ec11a-2011-4423-ba01-3af8de0a3e14",
"date": "2019-03-19T06:00+10:00",
"stockSymbol": "H",
"stockPrice": 72.83,
"strikePrice": 70.0,
"expiryDate": "2019-04-18T00:00+10:00",
"impliedVolatility": null,
"historicalImpliedVolatility": null,
"profitProbability": null,
"contracts": 1,
"premium": 0.65,
"action": "SELL",
"actionType": "PUT",
"brokerFees": 1.94,
"mark": 1
}
,
{
"transactionId": null,
"pairTransactionId": null,
"accountId": "d79ec11a-2011-4423-ba01-3af8de0a3e14",
"date": "2019-03-22T06:00+10:00",
"stockSymbol": "H",
"stockPrice": 0.0,
"strikePrice": 70.0,
"expiryDate": "2019-04-18T00:00+10:00",
"impliedVolatility": null,
"historicalImpliedVolatility": null,
"profitProbability": null,
"contracts": 1,
"premium": -0.56,
"action": "BUY",
"actionType": "PUT",
"brokerFees": 0.29,
"mark": 1
},

{
"transactionId": null,
"pairTransactionId": null,
"accountId": "d79ec11a-2011-4423-ba01-3af8de0a3e14",
"date": "2019-03-19T06:00+10:00",
"stockSymbol": "GNTX",
"stockPrice": 20.62,
"strikePrice": 20.0,
"expiryDate": "2019-04-18T00:00+10:00",
"impliedVolatility": null,
"historicalImpliedVolatility": null,
"profitProbability": null,
"contracts": 3,
"premium": 0.34,
"action": "SELL",
"actionType": "PUT",
"brokerFees": 2.37,
"mark": 1
}
,
{
"transactionId": null,
"pairTransactionId": null,
"accountId": "d79ec11a-2011-4423-ba01-3af8de0a3e14",
"date": "2019-04-04T06:00+10:00",
"stockSymbol": "GNTX",
"stockPrice": 0.0,
"strikePrice": 20.0,
"expiryDate": "2019-04-18T00:00+10:00",
"impliedVolatility": null,
"historicalImpliedVolatility": null,
"profitProbability": null,
"contracts": 3,
"premium": -0.10,
"action": "BUY",
"actionType": "PUT",
"brokerFees": 2.38,
"mark": 1
},

{
"transactionId": null,
"pairTransactionId": null,
"accountId": "d79ec11a-2011-4423-ba01-3af8de0a3e14",
"date": "2019-03-19T06:00+10:00",
"stockSymbol": "MGA",
"stockPrice": 49.35,
"strikePrice": 47.5,
"expiryDate": "2019-04-18T00:00+10:00",
"impliedVolatility": null,
"historicalImpliedVolatility": null,
"profitProbability": null,
"contracts": 1,
"premium": 0.55,
"action": "SELL",
"actionType": "PUT",
"brokerFees": 0.0,
"mark": 1
}
,
{
"transactionId": null,
"pairTransactionId": null,
"accountId": "d79ec11a-2011-4423-ba01-3af8de0a3e14",
"date": "2019-04-03T06:00+10:00",
"stockSymbol": "MGA",
"stockPrice": 0.0,
"strikePrice": 47.5,
"expiryDate": "2019-04-18T00:00+10:00",
"impliedVolatility": null,
"historicalImpliedVolatility": null,
"profitProbability": null,
"contracts": 1,
"premium": -0.19,
"action": "BUY",
"actionType": "PUT",
"brokerFees": 0.34,
"mark": 1
},

{
"transactionId": null,
"pairTransactionId": null,
"accountId": "d79ec11a-2011-4423-ba01-3af8de0a3e14",
"date": "2019-03-19T06:00+10:00",
"stockSymbol": "CVS",
"stockPrice": 56.57,
"strikePrice": 55.0,
"expiryDate": "2019-04-12T00:00+10:00",
"impliedVolatility": null,
"historicalImpliedVolatility": null,
"profitProbability": null,
"contracts": 1,
"premium": 0.85,
"action": "SELL",
"actionType": "PUT",
"brokerFees": 0.79,
"mark": 1
}
,
{
"transactionId": null,
"pairTransactionId": null,
"accountId": "d79ec11a-2011-4423-ba01-3af8de0a3e14",
"date": "2019-04-13T06:00+10:00",
"stockSymbol": "CVS",
"stockPrice": 0.0,
"strikePrice": 55.0,
"expiryDate": "2019-04-12T00:00+10:00",
"impliedVolatility": null,
"historicalImpliedVolatility": null,
"profitProbability": null,
"contracts": 1,
"premium": 0.00,
"action": "BUY",
"actionType": "PUT",
"brokerFees": 0.0,
"mark": 1
},

{
"transactionId": null,
"pairTransactionId": null,
"accountId": "d79ec11a-2011-4423-ba01-3af8de0a3e14",
"date": "2019-03-19T06:00+10:00",
"stockSymbol": "NBLX",
"stockPrice": 37.99,
"strikePrice": 35.0,
"expiryDate": "2019-05-17T00:00+10:00",
"impliedVolatility": null,
"historicalImpliedVolatility": null,
"profitProbability": null,
"contracts": 1,
"premium": 0.95,
"action": "SELL",
"actionType": "PUT",
"brokerFees": 0.29,
"mark": 1
}
,
{
"transactionId": null,
"pairTransactionId": null,
"accountId": "d79ec11a-2011-4423-ba01-3af8de0a3e14",
"date": "2019-04-19T06:00+10:00",
"stockSymbol": "NBLX",
"stockPrice": 0.0,
"strikePrice": 35.0,
"expiryDate": "2019-05-17T00:00+10:00",
"impliedVolatility": null,
"historicalImpliedVolatility": null,
"profitProbability": null,
"contracts": 1,
"premium": -0.65,
"action": "BUY",
"actionType": "PUT",
"brokerFees": 1.09,
"mark": 1
},

{
"transactionId": null,
"pairTransactionId": null,
"accountId": "d79ec11a-2011-4423-ba01-3af8de0a3e14",
"date": "2019-03-20T06:00+10:00",
"stockSymbol": "ABT",
"stockPrice": 80.15,
"strikePrice": 79.0,
"expiryDate": "2019-04-18T00:00+10:00",
"impliedVolatility": null,
"historicalImpliedVolatility": null,
"profitProbability": null,
"contracts": 1,
"premium": 1.41,
"action": "SELL",
"actionType": "PUT",
"brokerFees": 0.79,
"mark": 1
}
,
{
"transactionId": null,
"pairTransactionId": null,
"accountId": "d79ec11a-2011-4423-ba01-3af8de0a3e14",
"date": "2019-04-19T06:00+10:00",
"stockSymbol": "ABT",
"stockPrice": 0.0,
"strikePrice": 79.0,
"expiryDate": "2019-04-18T00:00+10:00",
"impliedVolatility": null,
"historicalImpliedVolatility": null,
"profitProbability": null,
"contracts": 1,
"premium": 0.00,
"action": "BUY",
"actionType": "PUT",
"brokerFees": 0.0,
"mark": 1
},

{
"transactionId": null,
"pairTransactionId": null,
"accountId": "d79ec11a-2011-4423-ba01-3af8de0a3e14",
"date": "2019-03-20T06:00+10:00",
"stockSymbol": "IP",
"stockPrice": 45.36,
"strikePrice": 45.5,
"expiryDate": "2019-04-05T00:00+10:00",
"impliedVolatility": null,
"historicalImpliedVolatility": null,
"profitProbability": null,
"contracts": 1,
"premium": 0.53,
"action": "SELL",
"actionType": "PUT",
"brokerFees": 0.79,
"mark": 1
}
,
{
"transactionId": null,
"pairTransactionId": null,
"accountId": "d79ec11a-2011-4423-ba01-3af8de0a3e14",
"date": "2019-03-30T06:00+10:00",
"stockSymbol": "IP",
"stockPrice": 0.0,
"strikePrice": 45.5,
"expiryDate": "2019-04-05T00:00+10:00",
"impliedVolatility": null,
"historicalImpliedVolatility": null,
"profitProbability": null,
"contracts": 1,
"premium": -0.28,
"action": "BUY",
"actionType": "PUT",
"brokerFees": 0.79,
"mark": 1
},

{
"transactionId": null,
"pairTransactionId": null,
"accountId": "d79ec11a-2011-4423-ba01-3af8de0a3e14",
"date": "2019-03-20T06:00+10:00",
"stockSymbol": "KO",
"stockPrice": 45.47,
"strikePrice": 45.0,
"expiryDate": "2019-04-18T00:00+10:00",
"impliedVolatility": null,
"historicalImpliedVolatility": null,
"profitProbability": null,
"contracts": 1,
"premium": 0.38,
"action": "SELL",
"actionType": "PUT",
"brokerFees": 1.09,
"mark": 1
}
,
{
"transactionId": null,
"pairTransactionId": null,
"accountId": "d79ec11a-2011-4423-ba01-3af8de0a3e14",
"date": "2019-03-26T06:00+10:00",
"stockSymbol": "KO",
"stockPrice": 0.0,
"strikePrice": 45.0,
"expiryDate": "2019-04-18T00:00+10:00",
"impliedVolatility": null,
"historicalImpliedVolatility": null,
"profitProbability": null,
"contracts": 1,
"premium": -0.26,
"action": "BUY",
"actionType": "PUT",
"brokerFees": 1.09,
"mark": 1
},

{
"transactionId": null,
"pairTransactionId": null,
"accountId": "d79ec11a-2011-4423-ba01-3af8de0a3e14",
"date": "2019-03-20T06:00+10:00",
"stockSymbol": "ICHR",
"stockPrice": 22.55,
"strikePrice": 20.0,
"expiryDate": "2019-04-18T00:00+10:00",
"impliedVolatility": null,
"historicalImpliedVolatility": null,
"profitProbability": null,
"contracts": 2,
"premium": 0.30,
"action": "SELL",
"actionType": "PUT",
"brokerFees": 1.58,
"mark": 1
}
,
{
"transactionId": null,
"pairTransactionId": null,
"accountId": "d79ec11a-2011-4423-ba01-3af8de0a3e14",
"date": "2019-03-30T06:00+10:00",
"stockSymbol": "ICHR",
"stockPrice": 0.0,
"strikePrice": 20.0,
"expiryDate": "2019-04-18T00:00+10:00",
"impliedVolatility": null,
"historicalImpliedVolatility": null,
"profitProbability": null,
"contracts": 2,
"premium": -0.19,
"action": "BUY",
"actionType": "PUT",
"brokerFees": -0.12,
"mark": 1
},

{
"transactionId": null,
"pairTransactionId": null,
"accountId": "d79ec11a-2011-4423-ba01-3af8de0a3e14",
"date": "2019-03-20T06:00+10:00",
"stockSymbol": "LKQ",
"stockPrice": 28.78,
"strikePrice": 27.5,
"expiryDate": "2019-04-18T00:00+10:00",
"impliedVolatility": null,
"historicalImpliedVolatility": null,
"profitProbability": null,
"contracts": 2,
"premium": 0.25,
"action": "SELL",
"actionType": "PUT",
"brokerFees": 0.08,
"mark": 1
}
,
{
"transactionId": null,
"pairTransactionId": null,
"accountId": "d79ec11a-2011-4423-ba01-3af8de0a3e14",
"date": "2019-04-02T06:00+10:00",
"stockSymbol": "LKQ",
"stockPrice": 0.0,
"strikePrice": 27.5,
"expiryDate": "2019-04-18T00:00+10:00",
"impliedVolatility": null,
"historicalImpliedVolatility": null,
"profitProbability": null,
"contracts": 2,
"premium": -0.10,
"action": "BUY",
"actionType": "PUT",
"brokerFees": 0.0,
"mark": 1
},

{
"transactionId": null,
"pairTransactionId": null,
"accountId": "d79ec11a-2011-4423-ba01-3af8de0a3e14",
"date": "2019-03-21T06:00+10:00",
"stockSymbol": "AEIS",
"stockPrice": 49.40,
"strikePrice": 45.0,
"expiryDate": "2019-04-18T00:00+10:00",
"impliedVolatility": null,
"historicalImpliedVolatility": null,
"profitProbability": null,
"contracts": 1,
"premium": 0.44,
"action": "SELL",
"actionType": "PUT",
"brokerFees": 0.29,
"mark": 1
}
,
{
"transactionId": null,
"pairTransactionId": null,
"accountId": "d79ec11a-2011-4423-ba01-3af8de0a3e14",
"date": "2019-04-03T06:00+10:00",
"stockSymbol": "AEIS",
"stockPrice": 0.0,
"strikePrice": 45.0,
"expiryDate": "2019-04-18T00:00+10:00",
"impliedVolatility": null,
"historicalImpliedVolatility": null,
"profitProbability": null,
"contracts": 1,
"premium": -0.25,
"action": "BUY",
"actionType": "PUT",
"brokerFees": 1.09,
"mark": 1
},

{
"transactionId": null,
"pairTransactionId": null,
"accountId": "d79ec11a-2011-4423-ba01-3af8de0a3e14",
"date": "2019-03-22T06:00+10:00",
"stockSymbol": "CYBR",
"stockPrice": 117.66,
"strikePrice": 112.0,
"expiryDate": "2019-04-12T00:00+10:00",
"impliedVolatility": null,
"historicalImpliedVolatility": null,
"profitProbability": null,
"contracts": 1,
"premium": 1.60,
"action": "SELL",
"actionType": "PUT",
"brokerFees": 0.29,
"mark": 1
}
,
{
"transactionId": null,
"pairTransactionId": null,
"accountId": "d79ec11a-2011-4423-ba01-3af8de0a3e14",
"date": "2019-04-02T06:00+10:00",
"stockSymbol": "CYBR",
"stockPrice": 0.0,
"strikePrice": 112.0,
"expiryDate": "2019-04-12T00:00+10:00",
"impliedVolatility": null,
"historicalImpliedVolatility": null,
"profitProbability": null,
"contracts": 1,
"premium": -0.75,
"action": "BUY",
"actionType": "PUT",
"brokerFees": -0.34,
"mark": 1
},

{
"transactionId": null,
"pairTransactionId": null,
"accountId": "d79ec11a-2011-4423-ba01-3af8de0a3e14",
"date": "2019-03-22T06:00+10:00",
"stockSymbol": "KEYS",
"stockPrice": 87.53,
"strikePrice": 82.5,
"expiryDate": "2019-04-18T00:00+10:00",
"impliedVolatility": null,
"historicalImpliedVolatility": null,
"profitProbability": null,
"contracts": 1,
"premium": 0.41,
"action": "SELL",
"actionType": "PUT",
"brokerFees": 0.24,
"mark": 1
}
,
{
"transactionId": null,
"pairTransactionId": null,
"accountId": "d79ec11a-2011-4423-ba01-3af8de0a3e14",
"date": "2019-04-02T06:00+10:00",
"stockSymbol": "KEYS",
"stockPrice": 0.0,
"strikePrice": 82.5,
"expiryDate": "2019-04-18T00:00+10:00",
"impliedVolatility": null,
"historicalImpliedVolatility": null,
"profitProbability": null,
"contracts": 1,
"premium": -0.20,
"action": "BUY",
"actionType": "PUT",
"brokerFees": -1.09,
"mark": 1
},

{
"transactionId": null,
"pairTransactionId": null,
"accountId": "d79ec11a-2011-4423-ba01-3af8de0a3e14",
"date": "2019-03-22T06:00+10:00",
"stockSymbol": "WLK",
"stockPrice": 69.81,
"strikePrice": 65.0,
"expiryDate": "2019-04-18T00:00+10:00",
"impliedVolatility": null,
"historicalImpliedVolatility": null,
"profitProbability": null,
"contracts": 1,
"premium": 0.62,
"action": "SELL",
"actionType": "PUT",
"brokerFees": 0.29,
"mark": 1
}
,
{
"transactionId": null,
"pairTransactionId": null,
"accountId": "d79ec11a-2011-4423-ba01-3af8de0a3e14",
"date": "2019-04-03T06:00+10:00",
"stockSymbol": "WLK",
"stockPrice": 0.0,
"strikePrice": 65.0,
"expiryDate": "2019-04-18T00:00+10:00",
"impliedVolatility": null,
"historicalImpliedVolatility": null,
"profitProbability": null,
"contracts": 1,
"premium": -0.35,
"action": "BUY",
"actionType": "PUT",
"brokerFees": 1.09,
"mark": 1
},

{
"transactionId": null,
"pairTransactionId": null,
"accountId": "d79ec11a-2011-4423-ba01-3af8de0a3e14",
"date": "2019-03-22T06:00+10:00",
"stockSymbol": "QNST",
"stockPrice": 13.72,
"strikePrice": 12.5,
"expiryDate": "2019-04-18T00:00+10:00",
"impliedVolatility": null,
"historicalImpliedVolatility": null,
"profitProbability": null,
"contracts": 3,
"premium": 0.20,
"action": "SELL",
"actionType": "PUT",
"brokerFees": 0.12,
"mark": 1
}
,
{
"transactionId": null,
"pairTransactionId": null,
"accountId": "d79ec11a-2011-4423-ba01-3af8de0a3e14",
"date": "2019-04-06T06:00+10:00",
"stockSymbol": "QNST",
"stockPrice": 0.0,
"strikePrice": 12.5,
"expiryDate": "2019-04-18T00:00+10:00",
"impliedVolatility": null,
"historicalImpliedVolatility": null,
"profitProbability": null,
"contracts": 3,
"premium": -0.10,
"action": "BUY",
"actionType": "PUT",
"brokerFees": 0.13,
"mark": 1
},

{
"transactionId": null,
"pairTransactionId": null,
"accountId": "d79ec11a-2011-4423-ba01-3af8de0a3e14",
"date": "2019-03-22T06:00+10:00",
"stockSymbol": "FOXF",
"stockPrice": 0.00,
"strikePrice": 65.0,
"expiryDate": "2019-04-18T00:00+10:00",
"impliedVolatility": null,
"historicalImpliedVolatility": null,
"profitProbability": null,
"contracts": 1,
"premium": 0.59,
"action": "SELL",
"actionType": "PUT",
"brokerFees": 0.0,
"mark": 1
}
,
{
"transactionId": null,
"pairTransactionId": null,
"accountId": "d79ec11a-2011-4423-ba01-3af8de0a3e14",
"date": "2019-04-06T06:00+10:00",
"stockSymbol": "FOXF",
"stockPrice": 0.0,
"strikePrice": 65.0,
"expiryDate": "2019-04-18T00:00+10:00",
"impliedVolatility": null,
"historicalImpliedVolatility": null,
"profitProbability": null,
"contracts": 1,
"premium": -0.10,
"action": "BUY",
"actionType": "PUT",
"brokerFees": 0.29,
"mark": 1
},

{
"transactionId": null,
"pairTransactionId": null,
"accountId": "d79ec11a-2011-4423-ba01-3af8de0a3e14",
"date": "2019-03-23T06:00+10:00",
"stockSymbol": "BERY",
"stockPrice": 53.68,
"strikePrice": 52.5,
"expiryDate": "2019-04-18T00:00+10:00",
"impliedVolatility": null,
"historicalImpliedVolatility": null,
"profitProbability": null,
"contracts": 1,
"premium": 0.70,
"action": "SELL",
"actionType": "PUT",
"brokerFees": 1.94,
"mark": 1
}
,
{
"transactionId": null,
"pairTransactionId": null,
"accountId": "d79ec11a-2011-4423-ba01-3af8de0a3e14",
"date": "2019-03-27T06:00+10:00",
"stockSymbol": "BERY",
"stockPrice": 0.0,
"strikePrice": 52.5,
"expiryDate": "2019-04-18T00:00+10:00",
"impliedVolatility": null,
"historicalImpliedVolatility": null,
"profitProbability": null,
"contracts": 1,
"premium": -0.48,
"action": "BUY",
"actionType": "PUT",
"brokerFees": 1.09,
"mark": 1
},

{
"transactionId": null,
"pairTransactionId": null,
"accountId": "d79ec11a-2011-4423-ba01-3af8de0a3e14",
"date": "2019-03-23T06:00+10:00",
"stockSymbol": "CRUS",
"stockPrice": 41.80,
"strikePrice": 40.0,
"expiryDate": "2019-04-05T00:00+10:00",
"impliedVolatility": null,
"historicalImpliedVolatility": null,
"profitProbability": null,
"contracts": 1,
"premium": 0.33,
"action": "SELL",
"actionType": "PUT",
"brokerFees": 0.29,
"mark": 1
}
,
{
"transactionId": null,
"pairTransactionId": null,
"accountId": "d79ec11a-2011-4423-ba01-3af8de0a3e14",
"date": "2019-03-27T06:00+10:00",
"stockSymbol": "CRUS",
"stockPrice": 0.0,
"strikePrice": 40.0,
"expiryDate": "2019-04-05T00:00+10:00",
"impliedVolatility": null,
"historicalImpliedVolatility": null,
"profitProbability": null,
"contracts": 1,
"premium": -0.24,
"action": "BUY",
"actionType": "PUT",
"brokerFees": 1.94,
"mark": 1
},

{
"transactionId": null,
"pairTransactionId": null,
"accountId": "d79ec11a-2011-4423-ba01-3af8de0a3e14",
"date": "2019-03-30T06:00+10:00",
"stockSymbol": "AMAT",
"stockPrice": 39.71,
"strikePrice": 38.0,
"expiryDate": "2019-04-12T00:00+10:00",
"impliedVolatility": null,
"historicalImpliedVolatility": null,
"profitProbability": null,
"contracts": 1,
"premium": 0.33,
"action": "SELL",
"actionType": "PUT",
"brokerFees": 0.79,
"mark": 1
}
,
{
"transactionId": null,
"pairTransactionId": null,
"accountId": "d79ec11a-2011-4423-ba01-3af8de0a3e14",
"date": "2019-04-02T06:00+10:00",
"stockSymbol": "AMAT",
"stockPrice": 0.0,
"strikePrice": 38.0,
"expiryDate": "2019-04-12T00:00+10:00",
"impliedVolatility": null,
"historicalImpliedVolatility": null,
"profitProbability": null,
"contracts": 1,
"premium": -0.11,
"action": "BUY",
"actionType": "PUT",
"brokerFees": 1.09,
"mark": 1
},

{
"transactionId": null,
"pairTransactionId": null,
"accountId": "d79ec11a-2011-4423-ba01-3af8de0a3e14",
"date": "2019-03-30T06:00+10:00",
"stockSymbol": "PLNT",
"stockPrice": 68.78,
"strikePrice": 65.0,
"expiryDate": "2019-04-18T00:00+10:00",
"impliedVolatility": null,
"historicalImpliedVolatility": null,
"profitProbability": null,
"contracts": 1,
"premium": 0.35,
"action": "SELL",
"actionType": "PUT",
"brokerFees": 0.34,
"mark": 1
}
,
{
"transactionId": null,
"pairTransactionId": null,
"accountId": "d79ec11a-2011-4423-ba01-3af8de0a3e14",
"date": "2019-04-03T06:00+10:00",
"stockSymbol": "PLNT",
"stockPrice": 0.0,
"strikePrice": 65.0,
"expiryDate": "2019-04-18T00:00+10:00",
"impliedVolatility": null,
"historicalImpliedVolatility": null,
"profitProbability": null,
"contracts": 1,
"premium": -0.15,
"action": "BUY",
"actionType": "PUT",
"brokerFees": 0.34,
"mark": 1
},

{
"transactionId": null,
"pairTransactionId": null,
"accountId": "d79ec11a-2011-4423-ba01-3af8de0a3e14",
"date": "2019-04-02T06:00+10:00",
"stockSymbol": "APOG",
"stockPrice": 38.21,
"strikePrice": 35.0,
"expiryDate": "2019-04-18T00:00+10:00",
"impliedVolatility": null,
"historicalImpliedVolatility": null,
"profitProbability": null,
"contracts": 1,
"premium": 0.78,
"action": "SELL",
"actionType": "PUT",
"brokerFees": 1.5,
"mark": 1
}
,
{
"transactionId": null,
"pairTransactionId": null,
"accountId": "d79ec11a-2011-4423-ba01-3af8de0a3e14",
"date": "2019-04-04T06:00+10:00",
"stockSymbol": "APOG",
"stockPrice": 0.0,
"strikePrice": 35.0,
"expiryDate": "2019-04-18T00:00+10:00",
"impliedVolatility": null,
"historicalImpliedVolatility": null,
"profitProbability": null,
"contracts": 1,
"premium": -0.65,
"action": "BUY",
"actionType": "PUT",
"brokerFees": 0.34,
"mark": 1
},

{
"transactionId": null,
"pairTransactionId": null,
"accountId": "d79ec11a-2011-4423-ba01-3af8de0a3e14",
"date": "2019-04-02T06:00+10:00",
"stockSymbol": "AYI",
"stockPrice": 123.47,
"strikePrice": 115.0,
"expiryDate": "2019-04-18T00:00+10:00",
"impliedVolatility": null,
"historicalImpliedVolatility": null,
"profitProbability": null,
"contracts": 1,
"premium": 2.20,
"action": "SELL",
"actionType": "PUT",
"brokerFees": 0.35,
"mark": 1
}
,
{
"transactionId": null,
"pairTransactionId": null,
"accountId": "d79ec11a-2011-4423-ba01-3af8de0a3e14",
"date": "2019-04-04T06:00+10:00",
"stockSymbol": "AYI",
"stockPrice": 0.0,
"strikePrice": 115.0,
"expiryDate": "2019-04-18T00:00+10:00",
"impliedVolatility": null,
"historicalImpliedVolatility": null,
"profitProbability": null,
"contracts": 1,
"premium": -0.10,
"action": "BUY",
"actionType": "PUT",
"brokerFees": 0.0,
"mark": 1
},

{
"transactionId": null,
"pairTransactionId": null,
"accountId": "d79ec11a-2011-4423-ba01-3af8de0a3e14",
"date": "2019-04-02T06:00+10:00",
"stockSymbol": "EXEL",
"stockPrice": 24.35,
"strikePrice": 24.0,
"expiryDate": "2019-04-18T00:00+10:00",
"impliedVolatility": null,
"historicalImpliedVolatility": null,
"profitProbability": null,
"contracts": 1,
"premium": 0.60,
"action": "SELL",
"actionType": "PUT",
"brokerFees": 0.6,
"mark": 1
}
,
{
"transactionId": null,
"pairTransactionId": null,
"accountId": "d79ec11a-2011-4423-ba01-3af8de0a3e14",
"date": "2019-04-04T06:00+10:00",
"stockSymbol": "EXEL",
"stockPrice": 0.0,
"strikePrice": 24.0,
"expiryDate": "2019-04-18T00:00+10:00",
"impliedVolatility": null,
"historicalImpliedVolatility": null,
"profitProbability": null,
"contracts": 1,
"premium": -0.48,
"action": "BUY",
"actionType": "PUT",
"brokerFees": 1.09,
"mark": 1
},

{
"transactionId": null,
"pairTransactionId": null,
"accountId": "d79ec11a-2011-4423-ba01-3af8de0a3e14",
"date": "2019-04-02T06:00+10:00",
"stockSymbol": "NUE",
"stockPrice": 59.53,
"strikePrice": 58.0,
"expiryDate": "2019-04-12T00:00+10:00",
"impliedVolatility": null,
"historicalImpliedVolatility": null,
"profitProbability": null,
"contracts": 1,
"premium": 0.40,
"action": "SELL",
"actionType": "PUT",
"brokerFees": 1.1,
"mark": 1
}
,
{
"transactionId": null,
"pairTransactionId": null,
"accountId": "d79ec11a-2011-4423-ba01-3af8de0a3e14",
"date": "2019-04-05T06:00+10:00",
"stockSymbol": "NUE",
"stockPrice": 0.0,
"strikePrice": 58.0,
"expiryDate": "2019-04-12T00:00+10:00",
"impliedVolatility": null,
"historicalImpliedVolatility": null,
"profitProbability": null,
"contracts": 1,
"premium": -0.19,
"action": "BUY",
"actionType": "PUT",
"brokerFees": 0.61,
"mark": 1
},

{
"transactionId": null,
"pairTransactionId": null,
"accountId": "d79ec11a-2011-4423-ba01-3af8de0a3e14",
"date": "2019-04-02T06:00+10:00",
"stockSymbol": "AGX",
"stockPrice": 50.71,
"strikePrice": 50.0,
"expiryDate": "2019-04-18T00:00+10:00",
"impliedVolatility": null,
"historicalImpliedVolatility": null,
"profitProbability": null,
"contracts": 1,
"premium": 1.65,
"action": "SELL",
"actionType": "PUT",
"brokerFees": 1.5,
"mark": 1
}
,
{
"transactionId": null,
"pairTransactionId": null,
"accountId": "d79ec11a-2011-4423-ba01-3af8de0a3e14",
"date": "2019-04-12T06:00+10:00",
"stockSymbol": "AGX",
"stockPrice": 0.0,
"strikePrice": 50.0,
"expiryDate": "2019-04-18T00:00+10:00",
"impliedVolatility": null,
"historicalImpliedVolatility": null,
"profitProbability": null,
"contracts": 1,
"premium": -0.80,
"action": "BUY",
"actionType": "PUT",
"brokerFees": 1.49,
"mark": 1
},

{
"transactionId": null,
"pairTransactionId": null,
"accountId": "d79ec11a-2011-4423-ba01-3af8de0a3e14",
"date": "2019-04-03T06:00+10:00",
"stockSymbol": "HIIQ",
"stockPrice": 25.55,
"strikePrice": 25.0,
"expiryDate": "2019-04-18T00:00+10:00",
"impliedVolatility": null,
"historicalImpliedVolatility": null,
"profitProbability": null,
"contracts": 1,
"premium": 2.35,
"action": "SELL",
"actionType": "PUT",
"brokerFees": 0.35,
"mark": 1
}
,
{
"transactionId": null,
"pairTransactionId": null,
"accountId": "d79ec11a-2011-4423-ba01-3af8de0a3e14",
"date": "2019-04-04T06:00+10:00",
"stockSymbol": "HIIQ",
"stockPrice": 0.0,
"strikePrice": 25.0,
"expiryDate": "2019-04-18T00:00+10:00",
"impliedVolatility": null,
"historicalImpliedVolatility": null,
"profitProbability": null,
"contracts": 1,
"premium": -1.95,
"action": "BUY",
"actionType": "PUT",
"brokerFees": 0.34,
"mark": 1
},

{
"transactionId": null,
"pairTransactionId": null,
"accountId": "d79ec11a-2011-4423-ba01-3af8de0a3e14",
"date": "2019-04-03T06:00+10:00",
"stockSymbol": "WBA",
"stockPrice": 55.42,
"strikePrice": 55.0,
"expiryDate": "2019-04-12T00:00+10:00",
"impliedVolatility": null,
"historicalImpliedVolatility": null,
"profitProbability": null,
"contracts": 1,
"premium": 0.85,
"action": "SELL",
"actionType": "PUT",
"brokerFees": 1.58,
"mark": 1
}
,
{
"transactionId": null,
"pairTransactionId": null,
"accountId": "d79ec11a-2011-4423-ba01-3af8de0a3e14",
"date": "2019-04-09T06:00+10:00",
"stockSymbol": "WBA",
"stockPrice": 0.0,
"strikePrice": 55.0,
"expiryDate": "2019-04-12T00:00+10:00",
"impliedVolatility": null,
"historicalImpliedVolatility": null,
"profitProbability": null,
"contracts": 1,
"premium": -0.50,
"action": "BUY",
"actionType": "PUT",
"brokerFees": 1.09,
"mark": 1
},

{
"transactionId": null,
"pairTransactionId": null,
"accountId": "d79ec11a-2011-4423-ba01-3af8de0a3e14",
"date": "2019-04-03T06:00+10:00",
"stockSymbol": "SMPL",
"stockPrice": 21.65,
"strikePrice": 20.0,
"expiryDate": "2019-04-18T00:00+10:00",
"impliedVolatility": null,
"historicalImpliedVolatility": null,
"profitProbability": null,
"contracts": 4,
"premium": 0.25,
"action": "SELL",
"actionType": "PUT",
"brokerFees": 0.22,
"mark": 1
}
,
{
"transactionId": null,
"pairTransactionId": null,
"accountId": "d79ec11a-2011-4423-ba01-3af8de0a3e14",
"date": "2019-04-05T06:00+10:00",
"stockSymbol": "SMPL",
"stockPrice": 0.0,
"strikePrice": 20.0,
"expiryDate": "2019-04-18T00:00+10:00",
"impliedVolatility": null,
"historicalImpliedVolatility": null,
"profitProbability": null,
"contracts": 4,
"premium": -0.09,
"action": "BUY",
"actionType": "PUT",
"brokerFees": 2.38,
"mark": 1
},

{
"transactionId": null,
"pairTransactionId": null,
"accountId": "d79ec11a-2011-4423-ba01-3af8de0a3e14",
"date": "2019-04-04T06:00+10:00",
"stockSymbol": "BERY",
"stockPrice": 54.78,
"strikePrice": 55.0,
"expiryDate": "2019-05-17T00:00+10:00",
"impliedVolatility": null,
"historicalImpliedVolatility": null,
"profitProbability": null,
"contracts": 1,
"premium": 2.00,
"action": "SELL",
"actionType": "PUT",
"brokerFees": 0.35,
"mark": 1
}
,
{
"transactionId": null,
"pairTransactionId": null,
"accountId": "d79ec11a-2011-4423-ba01-3af8de0a3e14",
"date": "2019-04-06T06:00+10:00",
"stockSymbol": "BERY",
"stockPrice": 0.0,
"strikePrice": 55.0,
"expiryDate": "2019-05-17T00:00+10:00",
"impliedVolatility": null,
"historicalImpliedVolatility": null,
"profitProbability": null,
"contracts": 1,
"premium": -1.60,
"action": "BUY",
"actionType": "PUT",
"brokerFees": 0.34,
"mark": 1
},

{
"transactionId": null,
"pairTransactionId": null,
"accountId": "d79ec11a-2011-4423-ba01-3af8de0a3e14",
"date": "2019-04-04T06:00+10:00",
"stockSymbol": "LEN",
"stockPrice": 49.71,
"strikePrice": 50.0,
"expiryDate": "2019-05-17T00:00+10:00",
"impliedVolatility": null,
"historicalImpliedVolatility": null,
"profitProbability": null,
"contracts": 1,
"premium": 2.03,
"action": "SELL",
"actionType": "PUT",
"brokerFees": 0.8,
"mark": 1
}
,
{
"transactionId": null,
"pairTransactionId": null,
"accountId": "d79ec11a-2011-4423-ba01-3af8de0a3e14",
"date": "2019-04-06T06:00+10:00",
"stockSymbol": "LEN",
"stockPrice": 0.0,
"strikePrice": 50.0,
"expiryDate": "2019-05-17T00:00+10:00",
"impliedVolatility": null,
"historicalImpliedVolatility": null,
"profitProbability": null,
"contracts": 1,
"premium": -1.20,
"action": "BUY",
"actionType": "PUT",
"brokerFees": 0.79,
"mark": 1
},

{
"transactionId": null,
"pairTransactionId": null,
"accountId": "d79ec11a-2011-4423-ba01-3af8de0a3e14",
"date": "2019-04-05T06:00+10:00",
"stockSymbol": "CSCO",
"stockPrice": 55.23,
"strikePrice": 54.5,
"expiryDate": "2019-04-12T00:00+10:00",
"impliedVolatility": null,
"historicalImpliedVolatility": null,
"profitProbability": null,
"contracts": 4,
"premium": 0.92,
"action": "SELL",
"actionType": "CALL",
"brokerFees": 2.99,
"mark": 1
}
,
{
"transactionId": null,
"pairTransactionId": null,
"accountId": "d79ec11a-2011-4423-ba01-3af8de0a3e14",
"date": "2019-04-13T06:00+10:00",
"stockSymbol": "CSCO",
"stockPrice": 0.0,
"strikePrice": 54.5,
"expiryDate": "2019-04-12T00:00+10:00",
"impliedVolatility": null,
"historicalImpliedVolatility": null,
"profitProbability": null,
"contracts": 4,
"premium": 0.00,
"action": "BUY",
"actionType": "CALL",
"brokerFees": 0.0,
"mark": 1
},

{
"transactionId": null,
"pairTransactionId": null,
"accountId": "d79ec11a-2011-4423-ba01-3af8de0a3e14",
"date": "2019-04-06T06:00+10:00",
"stockSymbol": "VZ",
"stockPrice": 58.89,
"strikePrice": 58.0,
"expiryDate": "2019-04-26T00:00+10:00",
"impliedVolatility": null,
"historicalImpliedVolatility": null,
"profitProbability": null,
"contracts": 1,
"premium": 0.91,
"action": "SELL",
"actionType": "PUT",
"brokerFees": 0.8,
"mark": 1
}
,
{
"transactionId": null,
"pairTransactionId": null,
"accountId": "d79ec11a-2011-4423-ba01-3af8de0a3e14",
"date": "2019-04-13T06:00+10:00",
"stockSymbol": "VZ",
"stockPrice": 0.0,
"strikePrice": 58.0,
"expiryDate": "2019-04-26T00:00+10:00",
"impliedVolatility": null,
"historicalImpliedVolatility": null,
"profitProbability": null,
"contracts": 1,
"premium": -0.63,
"action": "BUY",
"actionType": "PUT",
"brokerFees": 1.09,
"mark": 1
},

{
"transactionId": null,
"pairTransactionId": null,
"accountId": "d79ec11a-2011-4423-ba01-3af8de0a3e14",
"date": "2019-04-09T06:00+10:00",
"stockSymbol": "BERY",
"stockPrice": 56.11,
"strikePrice": 55.0,
"expiryDate": "2019-05-17T00:00+10:00",
"impliedVolatility": null,
"historicalImpliedVolatility": null,
"profitProbability": null,
"contracts": 2,
"premium": 1.35,
"action": "SELL",
"actionType": "PUT",
"brokerFees": 0.1,
"mark": 1
}
,
{
"transactionId": null,
"pairTransactionId": null,
"accountId": "d79ec11a-2011-4423-ba01-3af8de0a3e14",
"date": "2019-04-13T06:00+10:00",
"stockSymbol": "BERY",
"stockPrice": 0.0,
"strikePrice": 55.0,
"expiryDate": "2019-05-17T00:00+10:00",
"impliedVolatility": null,
"historicalImpliedVolatility": null,
"profitProbability": null,
"contracts": 2,
"premium": -0.77,
"action": "BUY",
"actionType": "PUT",
"brokerFees": -0.01,
"mark": 1
},

{
"transactionId": null,
"pairTransactionId": null,
"accountId": "d79ec11a-2011-4423-ba01-3af8de0a3e14",
"date": "2019-04-09T06:00+10:00",
"stockSymbol": "AMAT",
"stockPrice": 42.87,
"strikePrice": 42.0,
"expiryDate": "2019-05-10T00:00+10:00",
"impliedVolatility": null,
"historicalImpliedVolatility": null,
"profitProbability": null,
"contracts": 2,
"premium": 1.13,
"action": "SELL",
"actionType": "PUT",
"brokerFees": 0.99,
"mark": 1
}
,
{
"transactionId": null,
"pairTransactionId": null,
"accountId": "d79ec11a-2011-4423-ba01-3af8de0a3e14",
"date": "2019-04-17T06:00+10:00",
"stockSymbol": "AMAT",
"stockPrice": 0.0,
"strikePrice": 42.0,
"expiryDate": "2019-05-10T00:00+10:00",
"impliedVolatility": null,
"historicalImpliedVolatility": null,
"profitProbability": null,
"contracts": 2,
"premium": -0.77,
"action": "BUY",
"actionType": "PUT",
"brokerFees": 2.56,
"mark": 1
},

{
"transactionId": null,
"pairTransactionId": null,
"accountId": "d79ec11a-2011-4423-ba01-3af8de0a3e14",
"date": "2019-04-09T06:00+10:00",
"stockSymbol": "SWKS",
"stockPrice": 87.42,
"strikePrice": 85.0,
"expiryDate": "2019-04-26T00:00+10:00",
"impliedVolatility": null,
"historicalImpliedVolatility": null,
"profitProbability": null,
"contracts": 1,
"premium": 1.12,
"action": "SELL",
"actionType": "PUT",
"brokerFees": 0.3,
"mark": 1
}
,
{
"transactionId": null,
"pairTransactionId": null,
"accountId": "d79ec11a-2011-4423-ba01-3af8de0a3e14",
"date": "2019-04-13T06:00+10:00",
"stockSymbol": "SWKS",
"stockPrice": 0.0,
"strikePrice": 85.0,
"expiryDate": "2019-04-26T00:00+10:00",
"impliedVolatility": null,
"historicalImpliedVolatility": null,
"profitProbability": null,
"contracts": 1,
"premium": -0.60,
"action": "BUY",
"actionType": "PUT",
"brokerFees": 0.0,
"mark": 1
},

{
"transactionId": null,
"pairTransactionId": null,
"accountId": "d79ec11a-2011-4423-ba01-3af8de0a3e14",
"date": "2019-04-09T06:00+10:00",
"stockSymbol": "LKQ",
"stockPrice": 30.17,
"strikePrice": 30.0,
"expiryDate": "2019-05-17T00:00+10:00",
"impliedVolatility": null,
"historicalImpliedVolatility": null,
"profitProbability": null,
"contracts": 3,
"premium": 1.00,
"action": "SELL",
"actionType": "PUT",
"brokerFees": 2.39,
"mark": 1
}
,
{
"transactionId": null,
"pairTransactionId": null,
"accountId": "d79ec11a-2011-4423-ba01-3af8de0a3e14",
"date": "2019-04-13T06:00+10:00",
"stockSymbol": "LKQ",
"stockPrice": 0.0,
"strikePrice": 30.0,
"expiryDate": "2019-05-17T00:00+10:00",
"impliedVolatility": null,
"historicalImpliedVolatility": null,
"profitProbability": null,
"contracts": 3,
"premium": -0.80,
"action": "BUY",
"actionType": "PUT",
"brokerFees": 0.13,
"mark": 1
},

{
"transactionId": null,
"pairTransactionId": null,
"accountId": "d79ec11a-2011-4423-ba01-3af8de0a3e14",
"date": "2019-04-10T06:00+10:00",
"stockSymbol": "CERN",
"stockPrice": 63.28,
"strikePrice": 62.5,
"expiryDate": "2019-04-18T00:00+10:00",
"impliedVolatility": null,
"historicalImpliedVolatility": null,
"profitProbability": null,
"contracts": 1,
"premium": -0.60,
"action": "BUY",
"actionType": "PUT",
"brokerFees": 1.09,
"mark": 1
}
,
{
"transactionId": null,
"pairTransactionId": null,
"accountId": "d79ec11a-2011-4423-ba01-3af8de0a3e14",
"date": "2019-04-18T06:00+10:00",
"stockSymbol": "CERN",
"stockPrice": 0.0,
"strikePrice": 62.5,
"expiryDate": "2019-04-18T00:00+10:00",
"impliedVolatility": null,
"historicalImpliedVolatility": null,
"profitProbability": null,
"contracts": 1,
"premium": 0.00,
"action": "BUY",
"actionType": "PUT",
"brokerFees": 0.0,
"mark": 1
},

{
"transactionId": null,
"pairTransactionId": null,
"accountId": "d79ec11a-2011-4423-ba01-3af8de0a3e14",
"date": "2019-04-17T06:00+10:00",
"stockSymbol": "CVS",
"stockPrice": 53.95,
"strikePrice": 55.0,
"expiryDate": "2019-04-26T00:00+10:00",
"impliedVolatility": null,
"historicalImpliedVolatility": null,
"profitProbability": null,
"contracts": 1,
"premium": 0.33,
"action": "SELL",
"actionType": "CALL",
"brokerFees": 1.1,
"mark": 1
}
,
{
"transactionId": null,
"pairTransactionId": null,
"accountId": "d79ec11a-2011-4423-ba01-3af8de0a3e14",
"date": "2019-04-19T06:00+10:00",
"stockSymbol": "CVS",
"stockPrice": 0.0,
"strikePrice": 55.0,
"expiryDate": "2019-04-26T00:00+10:00",
"impliedVolatility": null,
"historicalImpliedVolatility": null,
"profitProbability": null,
"contracts": 1,
"premium": -0.09,
"action": "BUY",
"actionType": "CALL",
"brokerFees": 0.13,
"mark": 1
},

{
"transactionId": null,
"pairTransactionId": null,
"accountId": "d79ec11a-2011-4423-ba01-3af8de0a3e14",
"date": "2019-04-17T06:00+10:00",
"stockSymbol": "TOL",
"stockPrice": 38.28,
"strikePrice": 39.5,
"expiryDate": "2019-05-03T00:00+10:00",
"impliedVolatility": null,
"historicalImpliedVolatility": null,
"profitProbability": null,
"contracts": 1,
"premium": 0.30,
"action": "SELL",
"actionType": "CALL",
"brokerFees": 0.35,
"mark": 1
}
,
{
"transactionId": null,
"pairTransactionId": null,
"accountId": "d79ec11a-2011-4423-ba01-3af8de0a3e14",
"date": "2019-04-26T06:00+10:00",
"stockSymbol": "TOL",
"stockPrice": 0.0,
"strikePrice": 39.5,
"expiryDate": "2019-05-03T00:00+10:00",
"impliedVolatility": null,
"historicalImpliedVolatility": null,
"profitProbability": null,
"contracts": 1,
"premium": -0.07,
"action": "BUY",
"actionType": "CALL",
"brokerFees": 0.29,
"mark": 1
}]